{"subjects": [{"name": "Con01", "diagnosis": "Control", "event_source": "saved", "has_saved_events": true, "has_complete_events": true, "last_dose_raw": "-", "time_since_dose_min": null, "levodopa_off": false, "laterality_raw": "R", "laterality_side": "R", "mean_imi": 0.4189, "cv_imi": 0.0962, "seq_imi": 0.280635, "seqslope_imi": 0.004282, "mean_amplitude": 138.2613, "cv_amplitude": 0.1297, "seq_amplitude": 0.705154, "seqslope_amplitude": -0.019824, "mean_rel_amplitude": 0.9922, "cv_rel_amplitude": 0.0947, "seq_rel_amplitude": 0.036808, "seqslope_rel_amplitude": -0.002703, "mean_power": 197910.9277, "cv_power": 0.326, "seq_power": 0.796918, "seqslope_power": -0.053838, "mean_peak_open_vel": 1405.6295, "cv_peak_open_vel": 0.2231, "seq_peak_open_vel": 0.792232, "seqslope_peak_open_vel": -0.034013, "mean_peak_close_vel": -1583.1587, "cv_peak_close_vel": 0.2008, "seq_peak_close_vel": 0.543753, "seqslope_peak_close_vel": -0.02824, "mean_mean_open_vel": 717.9259, "cv_mean_open_vel": 0.2125, "seq_mean_open_vel": 0.707349, "seqslope_mean_open_vel": -0.032495, "mean_mean_close_vel": -908.6409, "cv_mean_close_vel": 0.1603, "seq_mean_close_vel": 0.505088, "seqslope_mean_close_vel": -0.019308, "frequency": 2.3872}, {"name": "Con02", "diagnosis": "Control", "event_source": "saved", "has_saved_events": true, "has_complete_events": true, "last_dose_raw": "-", "time_since_dose_min": null, "levodopa_off": false, "laterality_raw": "R", "laterality_side": "R", "mean_imi": 0.4367, "cv_imi": 0.1117, "seq_imi": null, "seqslope_imi": null, "mean_amplitude": 81.7467, "cv_amplitude": 0.0578, "seq_amplitude": null, "seqslope_amplitude": null, "mean_rel_amplitude": 1.011, "cv_rel_amplitude": 0.0746, "seq_rel_amplitude": null, "seqslope_rel_amplitude": null, "mean_power": 50874.445, "cv_power": 0.3811, "seq_power": null, "seqslope_power": null, "mean_peak_open_vel": 613.725, "cv_peak_open_vel": 0.3277, "seq_peak_open_vel": null, "seqslope_peak_open_vel": null, "mean_peak_close_vel": -815.975, "cv_peak_close_vel": 0.1484, "seq_peak_close_vel": null, "seqslope_peak_close_vel": null, "mean_mean_open_vel": 309.65, "cv_mean_open_vel": 0.3136, "seq_mean_open_vel": null, "seqslope_mean_open_vel": null, "mean_mean_close_vel": -697.435, "cv_mean_close_vel": 0.2258, "seq_mean_close_vel": null, "seqslope_mean_close_vel": null, "frequency": 2.2899}, {"name": "Con03", "diagnosis": "Control", "event_source": "saved", "has_saved_events": true, "has_complete_events": true, "last_dose_raw": null, "time_since_dose_min": null, "levodopa_off": false, "laterality_raw": "L", "laterality_side": "L", "mean_imi": 0.6018, "cv_imi": 0.1684, "seq_imi": 0.48074, "seqslope_imi": -0.063315, "mean_amplitude": 103.6571, "cv_amplitude": 0.1547, "seq_amplitude": 0.613849, "seqslope_amplitude": -0.074331, "mean_rel_amplitude": 1.0375, "cv_rel_amplitude": 0.3052, "seq_rel_amplitude": 0.175921, "seqslope_rel_amplitude": -0.054149, "mean_power": 113186.8314, "cv_power": 0.2685, "seq_power": 0.636722, "seqslope_power": -0.152654, "mean_peak_open_vel": 1079.4161, "cv_peak_open_vel": 0.2234, "seq_peak_open_vel": 0.283875, "seqslope_peak_open_vel": -0.078323, "mean_peak_close_vel": -1232.9089, "cv_peak_close_vel": 0.2666, "seq_peak_close_vel": 0.153476, "seqslope_peak_close_vel": 0.043511, "mean_mean_open_vel": 502.3171, "cv_mean_open_vel": 0.2078, "seq_mean_open_vel": 0.087235, "seqslope_mean_open_vel": -0.019919, "mean_mean_close_vel": -622.3396, "cv_mean_close_vel": 0.3682, "seq_mean_close_vel": 0.240416, "seqslope_mean_close_vel": -0.132098, "frequency": 1.6617}, {"name": "Con05", "diagnosis": "Control", "event_source": "saved", "has_saved_events": true, "has_complete_events": true, "last_dose_raw": null, "time_since_dose_min": null, "levodopa_off": true, "laterality_raw": "L", "laterality_side": "L", "mean_imi": 0.7372, "cv_imi": 0.5356, "seq_imi": 0.189171, "seqslope_imi": -0.060334, "mean_amplitude": 94.4143, "cv_amplitude": 0.2664, "seq_amplitude": 0.784078, "seqslope_amplitude": -0.044438, "mean_rel_amplitude": 1.0707, "cv_rel_amplitude": 0.2801, "seq_rel_amplitude": 0.038954, "seqslope_rel_amplitude": -0.009966, "mean_power": 84472.8623, "cv_power": 1.0446, "seq_power": 0.449149, "seqslope_power": -0.205375, "mean_peak_open_vel": 796.8808, "cv_peak_open_vel": 0.7941, "seq_peak_open_vel": 0.3589, "seqslope_peak_open_vel": -0.159388, "mean_peak_close_vel": -1237.8462, "cv_peak_close_vel": 0.8703, "seq_peak_close_vel": -0.022509, "seqslope_peak_close_vel": -0.013604, "mean_mean_open_vel": 300.6862, "cv_mean_open_vel": 0.3801, "seq_mean_open_vel": -0.091058, "seqslope_mean_open_vel": 0.026182, "mean_mean_close_vel": -445.4264, "cv_mean_close_vel": 0.6038, "seq_mean_close_vel": 0.067818, "seqslope_mean_close_vel": -0.091937, "frequency": 1.3565}, {"name": "Con08", "diagnosis": "Control", "event_source": "saved", "has_saved_events": true, "has_complete_events": true, "last_dose_raw": null, "time_since_dose_min": null, "levodopa_off": false, "laterality_raw": "L", "laterality_side": "L", "mean_imi": 0.3458, "cv_imi": 0.0592, "seq_imi": 0.039726, "seqslope_imi": -0.004242, "mean_amplitude": 152.8949, "cv_amplitude": 0.0912, "seq_amplitude": 0.569273, "seqslope_amplitude": -0.010162, "mean_rel_amplitude": 0.9985, "cv_rel_amplitude": 0.0934, "seq_rel_amplitude": 0.012221, "seqslope_rel_amplitude": 0.001132, "mean_power": 203142.4451, "cv_power": 0.203, "seq_power": 0.583457, "seqslope_power": -0.015059, "mean_peak_open_vel": 1318.92, "cv_peak_open_vel": 0.1369, "seq_peak_open_vel": 0.464271, "seqslope_peak_open_vel": -0.004897, "mean_peak_close_vel": -2055.85, "cv_peak_close_vel": 0.1025, "seq_peak_close_vel": 0.325599, "seqslope_peak_close_vel": -0.004829, "mean_mean_open_vel": 891.8689, "cv_mean_open_vel": 0.14, "seq_mean_open_vel": 0.143752, "seqslope_mean_open_vel": -0.005189, "mean_mean_close_vel": -1189.8749, "cv_mean_close_vel": 0.2451, "seq_mean_close_vel": 0.05117, "seqslope_mean_close_vel": 0.010886, "frequency": 2.8918}, {"name": "Con09", "diagnosis": "Control", "event_source": "saved", "has_saved_events": true, "has_complete_events": false, "last_dose_raw": null, "time_since_dose_min": null, "levodopa_off": false, "laterality_raw": "R", "laterality_side": "R", "mean_imi": 0.2246, "cv_imi": 0.123, "seq_imi": 0.090606, "seqslope_imi": -0.008346, "mean_amplitude": 91.4947, "cv_amplitude": 0.1466, "seq_amplitude": 0.480051, "seqslope_amplitude": -0.040247, "mean_rel_amplitude": 1.0235, "cv_rel_amplitude": 0.2053, "seq_rel_amplitude": 0.068184, "seqslope_rel_amplitude": -0.018334, "mean_power": null, "cv_power": null, "seq_power": null, "seqslope_power": null, "mean_peak_open_vel": null, "cv_peak_open_vel": null, "seq_peak_open_vel": null, "seqslope_peak_open_vel": null, "mean_peak_close_vel": null, "cv_peak_close_vel": null, "seq_peak_close_vel": null, "seqslope_peak_close_vel": null, "mean_mean_open_vel": null, "cv_mean_open_vel": null, "seq_mean_open_vel": null, "seqslope_mean_open_vel": null, "mean_mean_close_vel": null, "cv_mean_close_vel": null, "seq_mean_close_vel": null, "seqslope_mean_close_vel": null, "frequency": 4.4524}, {"name": "MSA01", "diagnosis": "MSA", "event_source": "saved", "has_saved_events": true, "has_complete_events": true, "last_dose_raw": null, "time_since_dose_min": null, "levodopa_off": false, "laterality_raw": "L", "laterality_side": "L", "mean_imi": 0.631, "cv_imi": 0.1502, "seq_imi": 0.07671, "seqslope_imi": -0.005437, "mean_amplitude": 75.2348, "cv_amplitude": 0.2527, "seq_amplitude": 0.709002, "seqslope_amplitude": -0.026414, "mean_rel_amplitude": 1.009, "cv_rel_amplitude": 0.223, "seq_rel_amplitude": -0.003228, "seqslope_rel_amplitude": 0.001834, "mean_power": 58038.8521, "cv_power": 0.4575, "seq_power": 0.177893, "seqslope_power": -0.028227, "mean_peak_open_vel": 762.9931, "cv_peak_open_vel": 0.3887, "seq_peak_open_vel": -0.040993, "seqslope_peak_open_vel": -0.001813, "mean_peak_close_vel": -859.5, "cv_peak_close_vel": 0.4896, "seq_peak_close_vel": 0.191366, "seqslope_peak_close_vel": -0.02914, "mean_mean_open_vel": 332.8248, "cv_mean_open_vel": 0.3773, "seq_mean_open_vel": 0.321438, "seqslope_mean_open_vel": -0.029017, "mean_mean_close_vel": -383.2586, "cv_mean_close_vel": 0.3715, "seq_mean_close_vel": -0.023156, "seqslope_mean_close_vel": 0.001045, "frequency": 1.5848}, {"name": "MSA02", "diagnosis": "MSA", "event_source": "saved", "has_saved_events": true, "has_complete_events": true, "last_dose_raw": null, "time_since_dose_min": null, "levodopa_off": true, "laterality_raw": "R", "laterality_side": "R", "mean_imi": 0.3092, "cv_imi": 0.1001, "seq_imi": 0.133485, "seqslope_imi": 0.006967, "mean_amplitude": 123.4071, "cv_amplitude": 0.1664, "seq_amplitude": 0.717118, "seqslope_amplitude": -0.040989, "mean_rel_amplitude": 1.0088, "cv_rel_amplitude": 0.1795, "seq_rel_amplitude": 0.048798, "seqslope_rel_amplitude": -0.009225, "mean_power": 157511.7427, "cv_power": 0.34, "seq_power": 0.567085, "seqslope_power": -0.073008, "mean_peak_open_vel": 1243.9829, "cv_peak_open_vel": 0.1979, "seq_peak_open_vel": 0.375383, "seqslope_peak_open_vel": -0.03202, "mean_peak_close_vel": -1499.0085, "cv_peak_close_vel": 0.2297, "seq_peak_close_vel": 0.564313, "seqslope_peak_close_vel": -0.054011, "mean_mean_open_vel": 883.4007, "cv_mean_open_vel": 0.2228, "seq_mean_open_vel": 0.493064, "seqslope_mean_open_vel": -0.038094, "mean_mean_close_vel": -1265.3922, "cv_mean_close_vel": 0.2342, "seq_mean_close_vel": 0.55563, "seqslope_mean_close_vel": -0.047133, "frequency": 3.2342}, {"name": "MSA03", "diagnosis": "MSA", "event_source": "auto", "has_saved_events": false, "has_complete_events": false, "last_dose_raw": null, "time_since_dose_min": null, "levodopa_off": false, "laterality_raw": "L", "laterality_side": "L", "mean_imi": 0.5491, "cv_imi": 0.4092, "seq_imi": 0.207293, "seqslope_imi": 0.07008, "mean_amplitude": 120.9797, "cv_amplitude": 0.294, "seq_amplitude": 0.572285, "seqslope_amplitude": -0.092758, "mean_rel_amplitude": 1.2124, "cv_rel_amplitude": 0.9332, "seq_rel_amplitude": 0.325641, "seqslope_rel_amplitude": -0.0741, "mean_power": 128980.5068, "cv_power": 0.5829, "seq_power": 0.47632, "seqslope_power": -0.237088, "mean_peak_open_vel": 979.7812, "cv_peak_open_vel": 0.4565, "seq_peak_open_vel": 0.519039, "seqslope_peak_open_vel": -0.14433, "mean_peak_close_vel": -1075.425, "cv_peak_close_vel": 0.5344, "seq_peak_close_vel": 0.153682, "seqslope_peak_close_vel": -0.119401, "mean_mean_open_vel": 809.8715, "cv_mean_open_vel": 1.4557, "seq_mean_open_vel": 0.279503, "seqslope_mean_open_vel": -0.098704, "mean_mean_close_vel": -958.47, "cv_mean_close_vel": 0.8325, "seq_mean_close_vel": 0.244564, "seqslope_mean_close_vel": -0.021814, "frequency": 1.8212}, {"name": "MSA04", "diagnosis": "MSA", "event_source": "saved", "has_saved_events": true, "has_complete_events": true, "last_dose_raw": null, "time_since_dose_min": null, "levodopa_off": false, "laterality_raw": "L", "laterality_side": "L", "mean_imi": 0.2344, "cv_imi": 0.317, "seq_imi": 0.310086, "seqslope_imi": -0.009258, "mean_amplitude": 77.2286, "cv_amplitude": 0.439, "seq_amplitude": 0.532029, "seqslope_amplitude": -0.017266, "mean_rel_amplitude": 1.1704, "cv_rel_amplitude": 0.6832, "seq_rel_amplitude": -0.058813, "seqslope_rel_amplitude": -0.000281, "mean_power": 74545.8173, "cv_power": 0.7239, "seq_power": 0.39243, "seqslope_power": -0.033332, "mean_peak_open_vel": 831.9342, "cv_peak_open_vel": 0.4555, "seq_peak_open_vel": 0.26541, "seqslope_peak_open_vel": -0.016066, "mean_peak_close_vel": -859.9443, "cv_peak_close_vel": 0.5171, "seq_peak_close_vel": 0.310771, "seqslope_peak_close_vel": -0.017335, "mean_mean_open_vel": 875.5613, "cv_mean_open_vel": 0.4923, "seq_mean_open_vel": 0.129643, "seqslope_mean_open_vel": -0.010286, "mean_mean_close_vel": -956.5371, "cv_mean_close_vel": 0.5083, "seq_mean_close_vel": 0.064431, "seqslope_mean_close_vel": -0.008464, "frequency": 4.2662}, {"name": "MSA05", "diagnosis": "MSA", "event_source": "saved", "has_saved_events": true, "has_complete_events": true, "last_dose_raw": null, "time_since_dose_min": null, "levodopa_off": true, "laterality_raw": "L", "laterality_side": "L", "mean_imi": 0.2649, "cv_imi": 0.1824, "seq_imi": 0.054973, "seqslope_imi": -0.00217, "mean_amplitude": 111.1767, "cv_amplitude": 0.2118, "seq_amplitude": 0.397937, "seqslope_amplitude": -0.011991, "mean_rel_amplitude": 1.0185, "cv_rel_amplitude": 0.1851, "seq_rel_amplitude": 0.012078, "seqslope_rel_amplitude": -0.006117, "mean_power": 159322.5061, "cv_power": 0.4423, "seq_power": 0.420842, "seqslope_power": -0.020792, "mean_peak_open_vel": 1378.7864, "cv_peak_open_vel": 0.2718, "seq_peak_open_vel": 0.348119, "seqslope_peak_open_vel": -0.008801, "mean_peak_close_vel": -1461.7864, "cv_peak_close_vel": 0.4965, "seq_peak_close_vel": 0.276841, "seqslope_peak_close_vel": -0.011716, "mean_mean_open_vel": 1129.5233, "cv_mean_open_vel": 0.1745, "seq_mean_open_vel": 0.239961, "seqslope_mean_open_vel": -0.00758, "mean_mean_close_vel": -1178.9424, "cv_mean_close_vel": 0.2218, "seq_mean_close_vel": 0.206328, "seqslope_mean_close_vel": -0.007921, "frequency": 3.775}, {"name": "MSA06", "diagnosis": "MSA", "event_source": "saved", "has_saved_events": true, "has_complete_events": true, "last_dose_raw": null, "time_since_dose_min": null, "levodopa_off": true, "laterality_raw": "L", "laterality_side": "L", "mean_imi": 0.486, "cv_imi": 0.4917, "seq_imi": 0.040398, "seqslope_imi": -0.020251, "mean_amplitude": 66.4482, "cv_amplitude": 0.3936, "seq_amplitude": 0.358298, "seqslope_amplitude": -0.056664, "mean_rel_amplitude": 1.1658, "cv_rel_amplitude": 0.6639, "seq_rel_amplitude": 0.056456, "seqslope_rel_amplitude": -0.042825, "mean_power": 38173.0037, "cv_power": 0.6162, "seq_power": 0.230068, "seqslope_power": -0.130045, "mean_peak_open_vel": 535.2488, "cv_peak_open_vel": 0.3672, "seq_peak_open_vel": 0.276469, "seqslope_peak_open_vel": -0.073381, "mean_peak_close_vel": -606.4807, "cv_peak_close_vel": 0.4241, "seq_peak_close_vel": 0.258732, "seqslope_peak_close_vel": -0.144714, "mean_mean_open_vel": 353.9598, "cv_mean_open_vel": 0.4261, "seq_mean_open_vel": 0.286188, "seqslope_mean_open_vel": -0.036317, "mean_mean_close_vel": -397.6634, "cv_mean_close_vel": 0.363, "seq_mean_close_vel": 0.367748, "seqslope_mean_close_vel": -0.068395, "frequency": 2.0576}, {"name": "MSA07", "diagnosis": "MSA", "event_source": "auto", "has_saved_events": false, "has_complete_events": false, "last_dose_raw": null, "time_since_dose_min": null, "levodopa_off": true, "laterality_raw": "R", "laterality_side": "R", "mean_imi": 0.4703, "cv_imi": 0.8821, "seq_imi": 0.18989, "seqslope_imi": -0.108945, "mean_amplitude": 45.8685, "cv_amplitude": 0.3552, "seq_amplitude": 0.570342, "seqslope_amplitude": -0.149946, "mean_rel_amplitude": 1.0961, "cv_rel_amplitude": 0.3749, "seq_rel_amplitude": 0.369474, "seqslope_rel_amplitude": -0.10019, "mean_power": 18125.4217, "cv_power": 0.9091, "seq_power": 0.423414, "seqslope_power": -0.339979, "mean_peak_open_vel": 340.55, "cv_peak_open_vel": 0.5679, "seq_peak_open_vel": 0.418332, "seqslope_peak_open_vel": -0.190033, "mean_peak_close_vel": -323.8431, "cv_peak_close_vel": 0.5923, "seq_peak_close_vel": -0.009787, "seqslope_peak_close_vel": -0.214836, "mean_mean_open_vel": 537.6341, "cv_mean_open_vel": 0.8883, "seq_mean_open_vel": 0.05492, "seqslope_mean_open_vel": -0.017942, "mean_mean_close_vel": -555.3491, "cv_mean_close_vel": 0.8735, "seq_mean_close_vel": 0.091668, "seqslope_mean_close_vel": 0.230088, "frequency": 2.1263}, {"name": "MSA08", "diagnosis": "MSA", "event_source": "saved", "has_saved_events": true, "has_complete_events": true, "last_dose_raw": "10am appt", "time_since_dose_min": null, "levodopa_off": false, "laterality_raw": "R", "laterality_side": "R", "mean_imi": 0.3701, "cv_imi": 0.2653, "seq_imi": 0.343086, "seqslope_imi": -0.061926, "mean_amplitude": 74.1959, "cv_amplitude": 0.394, "seq_amplitude": 0.571205, "seqslope_amplitude": -0.113054, "mean_rel_amplitude": 1.0563, "cv_rel_amplitude": 0.389, "seq_rel_amplitude": -0.001391, "seqslope_rel_amplitude": -0.00096, "mean_power": 61685.8932, "cv_power": 0.719, "seq_power": 0.491906, "seqslope_power": -0.161881, "mean_peak_open_vel": 762.5898, "cv_peak_open_vel": 0.4075, "seq_peak_open_vel": 0.337691, "seqslope_peak_open_vel": -0.048827, "mean_peak_close_vel": -863.8705, "cv_peak_close_vel": 0.3866, "seq_peak_close_vel": 0.42001, "seqslope_peak_close_vel": -0.095355, "mean_mean_open_vel": 439.0052, "cv_mean_open_vel": 0.2661, "seq_mean_open_vel": 0.174794, "seqslope_mean_open_vel": 0.016968, "mean_mean_close_vel": -656.4098, "cv_mean_close_vel": 0.4208, "seq_mean_close_vel": 0.254783, "seqslope_mean_close_vel": -0.129097, "frequency": 2.702}, {"name": "MSA09", "diagnosis": "MSA", "event_source": "saved", "has_saved_events": true, "has_complete_events": true, "last_dose_raw": "12:30 appt", "time_since_dose_min": null, "levodopa_off": false, "laterality_raw": "L", "laterality_side": "L", "mean_imi": 1.2036, "cv_imi": 0.214, "seq_imi": 0.680984, "seqslope_imi": 0.042556, "mean_amplitude": 85.34, "cv_amplitude": 0.2275, "seq_amplitude": 0.687936, "seqslope_amplitude": -0.045584, "mean_rel_amplitude": 0.9442, "cv_rel_amplitude": 0.1869, "seq_rel_amplitude": -0.032545, "seqslope_rel_amplitude": -0.00982, "mean_power": 50550.634, "cv_power": 0.4457, "seq_power": 0.354705, "seqslope_power": -0.076886, "mean_peak_open_vel": 577.69, "cv_peak_open_vel": 0.3463, "seq_peak_open_vel": 0.126782, "seqslope_peak_open_vel": -0.031302, "mean_peak_close_vel": -769.11, "cv_peak_close_vel": 0.4595, "seq_peak_close_vel": 0.349329, "seqslope_peak_close_vel": -0.072843, "mean_mean_open_vel": 158.6353, "cv_mean_open_vel": 0.375, "seq_mean_open_vel": 0.855435, "seqslope_mean_open_vel": -0.085253, "mean_mean_close_vel": -264.39, "cv_mean_close_vel": 0.4244, "seq_mean_close_vel": 0.704881, "seqslope_mean_close_vel": -0.093046, "frequency": 0.8308}, {"name": "MSA10", "diagnosis": "MSA", "event_source": "saved", "has_saved_events": true, "has_complete_events": true, "last_dose_raw": "-", "time_since_dose_min": null, "levodopa_off": true, "laterality_raw": "L", "laterality_side": "L", "mean_imi": 0.2449, "cv_imi": 0.1728, "seq_imi": 0.230182, "seqslope_imi": -0.019086, "mean_amplitude": 100.3247, "cv_amplitude": 0.2727, "seq_amplitude": 0.67046, "seqslope_amplitude": -0.048417, "mean_rel_amplitude": 1.0316, "cv_rel_amplitude": 0.245, "seq_rel_amplitude": 0.025318, "seqslope_rel_amplitude": -0.012909, "mean_power": 131552.315, "cv_power": 0.4967, "seq_power": 0.316985, "seqslope_power": -0.071595, "mean_peak_open_vel": 1250.0779, "cv_peak_open_vel": 0.2306, "seq_peak_open_vel": 0.142309, "seqslope_peak_open_vel": -0.023178, "mean_peak_close_vel": -1300.8309, "cv_peak_close_vel": 0.2625, "seq_peak_close_vel": 0.252362, "seqslope_peak_close_vel": -0.041639, "mean_mean_open_vel": 1026.4629, "cv_mean_open_vel": 0.1661, "seq_mean_open_vel": 0.272958, "seqslope_mean_open_vel": -0.021838, "mean_mean_close_vel": -1071.4953, "cv_mean_close_vel": 0.1985, "seq_mean_close_vel": 0.295563, "seqslope_mean_close_vel": -0.021664, "frequency": 4.0833}, {"name": "MSA11", "diagnosis": "MSA", "event_source": "auto", "has_saved_events": false, "has_complete_events": false, "last_dose_raw": "-", "time_since_dose_min": null, "levodopa_off": true, "laterality_raw": "R", "laterality_side": "R", "mean_imi": 0.4057, "cv_imi": 0.4247, "seq_imi": 0.329396, "seqslope_imi": -0.122559, "mean_amplitude": 106.4224, "cv_amplitude": 0.3383, "seq_amplitude": 0.546022, "seqslope_amplitude": -0.186974, "mean_rel_amplitude": 1.1905, "cv_rel_amplitude": 0.626, "seq_rel_amplitude": 0.194214, "seqslope_rel_amplitude": -0.155189, "mean_power": 110205.4556, "cv_power": 0.8443, "seq_power": 0.309276, "seqslope_power": -0.305969, "mean_peak_open_vel": 919.6597, "cv_peak_open_vel": 0.5864, "seq_peak_open_vel": 0.367797, "seqslope_peak_open_vel": -0.118995, "mean_peak_close_vel": -1066.5121, "cv_peak_close_vel": 0.5379, "seq_peak_close_vel": 0.548391, "seqslope_peak_close_vel": -0.208393, "mean_mean_open_vel": 812.5789, "cv_mean_open_vel": 1.5734, "seq_mean_open_vel": 0.199222, "seqslope_mean_open_vel": 0.039369, "mean_mean_close_vel": -973.2942, "cv_mean_close_vel": 0.6286, "seq_mean_close_vel": 0.329352, "seqslope_mean_close_vel": -0.062013, "frequency": 2.4649}, {"name": "MSA12", "diagnosis": "MSA", "event_source": "saved", "has_saved_events": true, "has_complete_events": true, "last_dose_raw": "10am appt", "time_since_dose_min": null, "levodopa_off": false, "laterality_raw": "R", "laterality_side": "R", "mean_imi": 0.5161, "cv_imi": 0.1077, "seq_imi": 0.421676, "seqslope_imi": 0.007638, "mean_amplitude": 113.4412, "cv_amplitude": 0.1056, "seq_amplitude": 0.683328, "seqslope_amplitude": -0.028344, "mean_rel_amplitude": 0.9971, "cv_rel_amplitude": 0.0859, "seq_rel_amplitude": 0.042143, "seqslope_rel_amplitude": -0.006859, "mean_power": 100870.7369, "cv_power": 0.2862, "seq_power": 0.125522, "seqslope_power": -0.009906, "mean_peak_open_vel": 883.125, "cv_peak_open_vel": 0.2438, "seq_peak_open_vel": 0.075167, "seqslope_peak_open_vel": 0.018437, "mean_peak_close_vel": -1004.3203, "cv_peak_close_vel": 0.2106, "seq_peak_close_vel": 0.146889, "seqslope_peak_close_vel": 0.002502, "mean_mean_open_vel": 493.2822, "cv_mean_open_vel": 0.2473, "seq_mean_open_vel": 0.484356, "seqslope_mean_open_vel": -0.023518, "mean_mean_close_vel": -563.6816, "cv_mean_close_vel": 0.2664, "seq_mean_close_vel": 0.245626, "seqslope_mean_close_vel": -0.046164, "frequency": 1.9376}, {"name": "MSA14", "diagnosis": "MSA", "event_source": "auto", "has_saved_events": false, "has_complete_events": false, "last_dose_raw": null, "time_since_dose_min": null, "levodopa_off": false, "laterality_raw": "R", "laterality_side": "R", "mean_imi": 0.2833, "cv_imi": 0.4273, "seq_imi": 0.074675, "seqslope_imi": -0.034109, "mean_amplitude": 51.7362, "cv_amplitude": 0.4308, "seq_amplitude": 0.688525, "seqslope_amplitude": -0.124987, "mean_rel_amplitude": 1.0878, "cv_rel_amplitude": 0.4502, "seq_rel_amplitude": 0.094887, "seqslope_rel_amplitude": -0.047966, "mean_power": 33540.1476, "cv_power": 1.0844, "seq_power": 0.535281, "seqslope_power": -0.278789, "mean_peak_open_vel": 526.605, "cv_peak_open_vel": 0.6135, "seq_peak_open_vel": 0.473123, "seqslope_peak_open_vel": -0.157257, "mean_peak_close_vel": -536.4673, "cv_peak_close_vel": 0.6025, "seq_peak_close_vel": 0.467626, "seqslope_peak_close_vel": -0.143941, "mean_mean_open_vel": 705.3128, "cv_mean_open_vel": 0.9578, "seq_mean_open_vel": -0.062076, "seqslope_mean_open_vel": 0.004181, "mean_mean_close_vel": -864.1484, "cv_mean_close_vel": 0.7668, "seq_mean_close_vel": 0.153098, "seqslope_mean_close_vel": -0.132111, "frequency": 3.5298}, {"name": "MSA15", "diagnosis": "MSA", "event_source": "auto", "has_saved_events": false, "has_complete_events": false, "last_dose_raw": null, "time_since_dose_min": null, "levodopa_off": false, "laterality_raw": "L", "laterality_side": "L", "mean_imi": 0.6741, "cv_imi": 0.3494, "seq_imi": 0.42723, "seqslope_imi": -0.160761, "mean_amplitude": 92.8786, "cv_amplitude": 0.2905, "seq_amplitude": 0.388762, "seqslope_amplitude": -0.149682, "mean_rel_amplitude": 1.1824, "cv_rel_amplitude": 0.5804, "seq_rel_amplitude": 0.40339, "seqslope_rel_amplitude": -0.149893, "mean_power": 60018.3914, "cv_power": 0.5022, "seq_power": -0.073841, "seqslope_power": -0.146333, "mean_peak_open_vel": 606.3375, "cv_peak_open_vel": 0.4035, "seq_peak_open_vel": 0.049763, "seqslope_peak_open_vel": -0.026908, "mean_peak_close_vel": -654.1768, "cv_peak_close_vel": 0.3378, "seq_peak_close_vel": 0.196553, "seqslope_peak_close_vel": -0.116816, "mean_mean_open_vel": 543.7418, "cv_mean_open_vel": 1.2157, "seq_mean_open_vel": 0.299373, "seqslope_mean_open_vel": 0.285645, "mean_mean_close_vel": -471.1911, "cv_mean_close_vel": 0.7293, "seq_mean_close_vel": 0.189111, "seqslope_mean_close_vel": 0.125513, "frequency": 1.4835}, {"name": "MSA16", "diagnosis": "MSA", "event_source": "auto", "has_saved_events": false, "has_complete_events": false, "last_dose_raw": null, "time_since_dose_min": null, "levodopa_off": false, "laterality_raw": "R", "laterality_side": "R", "mean_imi": 0.2939, "cv_imi": 0.2802, "seq_imi": 0.156518, "seqslope_imi": -0.011815, "mean_amplitude": 146.6784, "cv_amplitude": 0.0993, "seq_amplitude": 0.579709, "seqslope_amplitude": -0.033395, "mean_rel_amplitude": 1.0049, "cv_rel_amplitude": 0.1298, "seq_rel_amplitude": 0.239124, "seqslope_rel_amplitude": -0.017528, "mean_power": 240339.7029, "cv_power": 0.181, "seq_power": 0.368436, "seqslope_power": -0.048391, "mean_peak_open_vel": 1630.38, "cv_peak_open_vel": 0.126, "seq_peak_open_vel": 0.154428, "seqslope_peak_open_vel": -0.014996, "mean_peak_close_vel": -1836.6733, "cv_peak_close_vel": 0.1159, "seq_peak_close_vel": 0.284285, "seqslope_peak_close_vel": -0.023127, "mean_mean_open_vel": 1043.8553, "cv_mean_open_vel": 0.2903, "seq_mean_open_vel": 0.104425, "seqslope_mean_open_vel": 0.04479, "mean_mean_close_vel": -1437.8153, "cv_mean_close_vel": 0.3267, "seq_mean_close_vel": 0.042289, "seqslope_mean_close_vel": -0.040354, "frequency": 3.4025}, {"name": "MSA17", "diagnosis": "MSA", "event_source": "auto", "has_saved_events": false, "has_complete_events": false, "last_dose_raw": null, "time_since_dose_min": null, "levodopa_off": false, "laterality_raw": "R", "laterality_side": "R", "mean_imi": 0.2415, "cv_imi": 0.2912, "seq_imi": 0.021266, "seqslope_imi": -0.002679, "mean_amplitude": 84.5258, "cv_amplitude": 0.2757, "seq_amplitude": 0.509929, "seqslope_amplitude": -0.011276, "mean_rel_amplitude": 1.0182, "cv_rel_amplitude": 0.2229, "seq_rel_amplitude": -0.012424, "seqslope_rel_amplitude": 0.00033, "mean_power": 91315.887, "cv_power": 0.6513, "seq_power": 0.333505, "seqslope_power": -0.023626, "mean_peak_open_vel": 1005.25, "cv_peak_open_vel": 0.4258, "seq_peak_open_vel": 0.217016, "seqslope_peak_open_vel": -0.01235, "mean_peak_close_vel": -1147.1075, "cv_peak_close_vel": 0.422, "seq_peak_close_vel": 0.327454, "seqslope_peak_close_vel": -0.014347, "mean_mean_open_vel": 668.8615, "cv_mean_open_vel": 0.4172, "seq_mean_open_vel": 0.169472, "seqslope_mean_open_vel": -0.008332, "mean_mean_close_vel": -1519.1315, "cv_mean_close_vel": 0.663, "seq_mean_close_vel": -0.022264, "seqslope_mean_close_vel": -0.007842, "frequency": 4.1408}, {"name": "MSA18", "diagnosis": "MSA", "event_source": "auto", "has_saved_events": false, "has_complete_events": false, "last_dose_raw": null, "time_since_dose_min": null, "levodopa_off": false, "laterality_raw": "R", "laterality_side": "R", "mean_imi": 0.4493, "cv_imi": 0.3716, "seq_imi": 0.255084, "seqslope_imi": -0.244434, "mean_amplitude": 86.3477, "cv_amplitude": 0.6505, "seq_amplitude": 0.342006, "seqslope_amplitude": -0.342239, "mean_rel_amplitude": 2.717, "cv_rel_amplitude": 1.2376, "seq_rel_amplitude": 0.075841, "seqslope_rel_amplitude": -0.309865, "mean_power": 92385.035, "cv_power": 1.0109, "seq_power": 0.077514, "seqslope_power": -0.656568, "mean_peak_open_vel": 776.1577, "cv_peak_open_vel": 0.7166, "seq_peak_open_vel": 0.191975, "seqslope_peak_open_vel": -0.314328, "mean_peak_close_vel": -953.886, "cv_peak_close_vel": 0.979, "seq_peak_close_vel": 0.53084, "seqslope_peak_close_vel": -0.627352, "mean_mean_open_vel": 464.0019, "cv_mean_open_vel": 1.1229, "seq_mean_open_vel": 0.212871, "seqslope_mean_open_vel": 0.136735, "mean_mean_close_vel": -589.8924, "cv_mean_close_vel": 0.761, "seq_mean_close_vel": 0.430482, "seqslope_mean_close_vel": -0.317902, "frequency": 2.2257}, {"name": "PD01", "diagnosis": "PD", "event_source": "saved", "has_saved_events": true, "has_complete_events": true, "last_dose_raw": "5h 30m", "time_since_dose_min": 330.0, "levodopa_off": false, "laterality_raw": "R", "laterality_side": "R", "mean_imi": 0.2476, "cv_imi": 0.1068, "seq_imi": 0.080623, "seqslope_imi": -0.002234, "mean_amplitude": 84.7952, "cv_amplitude": 0.2679, "seq_amplitude": 0.507018, "seqslope_amplitude": -0.016418, "mean_rel_amplitude": 1.0787, "cv_rel_amplitude": 0.4375, "seq_rel_amplitude": -0.024175, "seqslope_rel_amplitude": 0.000701, "mean_power": 84936.9143, "cv_power": 0.4174, "seq_power": 0.425417, "seqslope_power": -0.02686, "mean_peak_open_vel": 957.55, "cv_peak_open_vel": 0.2188, "seq_peak_open_vel": 0.207858, "seqslope_peak_open_vel": -0.010442, "mean_peak_close_vel": -963.5393, "cv_peak_close_vel": 0.2223, "seq_peak_close_vel": 0.444211, "seqslope_peak_close_vel": -0.013812, "mean_mean_open_vel": 772.9288, "cv_mean_open_vel": 0.2177, "seq_mean_open_vel": 0.147937, "seqslope_mean_open_vel": -0.008174, "mean_mean_close_vel": -771.8548, "cv_mean_close_vel": 0.2859, "seq_mean_close_vel": 0.49707, "seqslope_mean_close_vel": -0.013548, "frequency": 4.0388}, {"name": "PD02", "diagnosis": "PD", "event_source": "saved", "has_saved_events": true, "has_complete_events": true, "last_dose_raw": "5h", "time_since_dose_min": 300.0, "levodopa_off": false, "laterality_raw": "R", "laterality_side": "R", "mean_imi": 0.908, "cv_imi": 0.2882, "seq_imi": 0.056931, "seqslope_imi": -0.023006, "mean_amplitude": 81.5367, "cv_amplitude": 0.2816, "seq_amplitude": 0.561689, "seqslope_amplitude": -0.059661, "mean_rel_amplitude": 1.0274, "cv_rel_amplitude": 0.3806, "seq_rel_amplitude": 0.015271, "seqslope_rel_amplitude": -0.021432, "mean_power": 51308.3329, "cv_power": 0.5408, "seq_power": 0.333649, "seqslope_power": -0.101523, "mean_peak_open_vel": 590.35, "cv_peak_open_vel": 0.3425, "seq_peak_open_vel": 0.207441, "seqslope_peak_open_vel": -0.041862, "mean_peak_close_vel": -575.3375, "cv_peak_close_vel": 0.4217, "seq_peak_close_vel": 0.28594, "seqslope_peak_close_vel": -0.022772, "mean_mean_open_vel": 349.7958, "cv_mean_open_vel": 0.467, "seq_mean_open_vel": 0.024647, "seqslope_mean_open_vel": -0.016094, "mean_mean_close_vel": -217.3083, "cv_mean_close_vel": 0.5104, "seq_mean_close_vel": -0.010253, "seqslope_mean_close_vel": -0.003638, "frequency": 1.1013}, {"name": "PD03", "diagnosis": "PD", "event_source": "saved", "has_saved_events": true, "has_complete_events": true, "last_dose_raw": "2h", "time_since_dose_min": 120.0, "levodopa_off": false, "laterality_raw": "L", "laterality_side": "L", "mean_imi": 0.5679, "cv_imi": 0.0668, "seq_imi": null, "seqslope_imi": null, "mean_amplitude": 134.1136, "cv_amplitude": 0.0673, "seq_amplitude": null, "seqslope_amplitude": null, "mean_rel_amplitude": 0.9962, "cv_rel_amplitude": 0.0785, "seq_rel_amplitude": null, "seqslope_rel_amplitude": null, "mean_power": 103829.8954, "cv_power": 0.2162, "seq_power": null, "seqslope_power": null, "mean_peak_open_vel": 769.9438, "cv_peak_open_vel": 0.1648, "seq_peak_open_vel": null, "seqslope_peak_open_vel": null, "mean_peak_close_vel": -1427.0688, "cv_peak_close_vel": 0.3186, "seq_peak_close_vel": null, "seqslope_peak_close_vel": null, "mean_mean_open_vel": 444.7288, "cv_mean_open_vel": 0.1307, "seq_mean_open_vel": null, "seqslope_mean_open_vel": null, "mean_mean_close_vel": -1006.36, "cv_mean_close_vel": 0.1168, "seq_mean_close_vel": null, "seqslope_mean_close_vel": null, "frequency": 1.7609}, {"name": "PD05", "diagnosis": "PD", "event_source": "saved", "has_saved_events": true, "has_complete_events": true, "last_dose_raw": "-", "time_since_dose_min": null, "levodopa_off": true, "laterality_raw": "L", "laterality_side": "L", "mean_imi": 0.7227, "cv_imi": 0.1079, "seq_imi": null, "seqslope_imi": null, "mean_amplitude": 131.374, "cv_amplitude": 0.056, "seq_amplitude": null, "seqslope_amplitude": null, "mean_rel_amplitude": 1.014, "cv_rel_amplitude": 0.0966, "seq_rel_amplitude": null, "seqslope_rel_amplitude": null, "mean_power": 134485.711, "cv_power": 0.3706, "seq_power": null, "seqslope_power": null, "mean_peak_open_vel": 1015.275, "cv_peak_open_vel": 0.3283, "seq_peak_open_vel": null, "seqslope_peak_open_vel": null, "mean_peak_close_vel": -2091.015, "cv_peak_close_vel": 0.5781, "seq_peak_close_vel": null, "seqslope_peak_close_vel": null, "mean_mean_open_vel": 411.766, "cv_mean_open_vel": 0.2298, "seq_mean_open_vel": null, "seqslope_mean_open_vel": null, "mean_mean_close_vel": -540.061, "cv_mean_close_vel": 0.1213, "seq_mean_close_vel": null, "seqslope_mean_close_vel": null, "frequency": 1.3837}, {"name": "PD06", "diagnosis": "PD", "event_source": "saved", "has_saved_events": true, "has_complete_events": true, "last_dose_raw": "6h", "time_since_dose_min": 360.0, "levodopa_off": false, "laterality_raw": "R", "laterality_side": "R", "mean_imi": 0.5923, "cv_imi": 0.3685, "seq_imi": 0.208587, "seqslope_imi": -0.003328, "mean_amplitude": 61.1895, "cv_amplitude": 0.5493, "seq_amplitude": 0.835098, "seqslope_amplitude": -0.134938, "mean_rel_amplitude": 1.0198, "cv_rel_amplitude": 0.4487, "seq_rel_amplitude": 0.092229, "seqslope_rel_amplitude": -0.005909, "mean_power": 39617.9153, "cv_power": 0.8686, "seq_power": 0.580537, "seqslope_power": -0.264421, "mean_peak_open_vel": 505.9145, "cv_peak_open_vel": 0.5852, "seq_peak_open_vel": 0.676146, "seqslope_peak_open_vel": -0.129483, "mean_peak_close_vel": -600.1263, "cv_peak_close_vel": 0.6382, "seq_peak_close_vel": 0.870183, "seqslope_peak_close_vel": -0.147061, "mean_mean_open_vel": 230.9797, "cv_mean_open_vel": 0.4754, "seq_mean_open_vel": 0.620787, "seqslope_mean_open_vel": -0.092765, "mean_mean_close_vel": -322.17, "cv_mean_close_vel": 0.5884, "seq_mean_close_vel": 0.602527, "seqslope_mean_close_vel": -0.148689, "frequency": 1.6883}, {"name": "PD07", "diagnosis": "PD", "event_source": "saved", "has_saved_events": true, "has_complete_events": true, "last_dose_raw": "-", "time_since_dose_min": null, "levodopa_off": true, "laterality_raw": "L", "laterality_side": "L", "mean_imi": 0.3006, "cv_imi": 0.3572, "seq_imi": 0.504751, "seqslope_imi": -0.140649, "mean_amplitude": 63.5711, "cv_amplitude": 0.204, "seq_amplitude": 0.856286, "seqslope_amplitude": -0.086649, "mean_rel_amplitude": 1.0484, "cv_rel_amplitude": 0.3375, "seq_rel_amplitude": 0.137486, "seqslope_rel_amplitude": -0.024519, "mean_power": 34228.1454, "cv_power": 0.4116, "seq_power": 0.798286, "seqslope_power": -0.191046, "mean_peak_open_vel": 516.3375, "cv_peak_open_vel": 0.2926, "seq_peak_open_vel": 0.565304, "seqslope_peak_open_vel": -0.104397, "mean_peak_close_vel": -613.8696, "cv_peak_close_vel": 0.3279, "seq_peak_close_vel": 0.578464, "seqslope_peak_close_vel": -0.110943, "mean_mean_open_vel": 525.8614, "cv_mean_open_vel": 0.3207, "seq_mean_open_vel": 0.312008, "seqslope_mean_open_vel": 0.082426, "mean_mean_close_vel": -891.3921, "cv_mean_close_vel": 0.3448, "seq_mean_close_vel": 0.0095, "seqslope_mean_close_vel": 0.011763, "frequency": 3.3267}, {"name": "PD08", "diagnosis": "PD", "event_source": "saved", "has_saved_events": true, "has_complete_events": true, "last_dose_raw": "1h 30m", "time_since_dose_min": 90.0, "levodopa_off": false, "laterality_raw": "L", "laterality_side": "L", "mean_imi": 0.2639, "cv_imi": 0.1167, "seq_imi": 0.089594, "seqslope_imi": -0.005198, "mean_amplitude": 102.4843, "cv_amplitude": 0.1334, "seq_amplitude": 0.634876, "seqslope_amplitude": -0.019128, "mean_rel_amplitude": 0.9947, "cv_rel_amplitude": 0.1185, "seq_rel_amplitude": 0.075166, "seqslope_rel_amplitude": -0.012855, "mean_power": 118474.4741, "cv_power": 0.3324, "seq_power": 0.276975, "seqslope_power": -0.025296, "mean_peak_open_vel": 1135.7027, "cv_peak_open_vel": 0.2283, "seq_peak_open_vel": 0.054701, "seqslope_peak_open_vel": -0.006169, "mean_peak_close_vel": -1217.4973, "cv_peak_close_vel": 0.2113, "seq_peak_close_vel": 0.253835, "seqslope_peak_close_vel": 0.006985, "mean_mean_open_vel": 1026.5692, "cv_mean_open_vel": 0.2209, "seq_mean_open_vel": 0.200591, "seqslope_mean_open_vel": -0.009627, "mean_mean_close_vel": -1131.5849, "cv_mean_close_vel": 0.3047, "seq_mean_close_vel": 0.045891, "seqslope_mean_close_vel": -0.084334, "frequency": 3.7893}, {"name": "PD09", "diagnosis": "PD", "event_source": "saved", "has_saved_events": true, "has_complete_events": true, "last_dose_raw": "45m", "time_since_dose_min": 45.0, "levodopa_off": false, "laterality_raw": "L", "laterality_side": "L", "mean_imi": 0.3438, "cv_imi": 0.0615, "seq_imi": null, "seqslope_imi": null, "mean_amplitude": 135.645, "cv_amplitude": 0.0674, "seq_amplitude": null, "seqslope_amplitude": null, "mean_rel_amplitude": 0.9714, "cv_rel_amplitude": 0.0472, "seq_rel_amplitude": null, "seqslope_rel_amplitude": null, "mean_power": 156831.315, "cv_power": 0.4494, "seq_power": null, "seqslope_power": null, "mean_peak_open_vel": 1180.8188, "cv_peak_open_vel": 0.4593, "seq_peak_open_vel": null, "seqslope_peak_open_vel": null, "mean_peak_close_vel": -1836.825, "cv_peak_close_vel": 0.0618, "seq_peak_close_vel": null, "seqslope_peak_close_vel": null, "mean_mean_open_vel": 888.3925, "cv_mean_open_vel": 0.1126, "seq_mean_open_vel": null, "seqslope_mean_open_vel": null, "mean_mean_close_vel": -1354.3112, "cv_mean_close_vel": 0.1697, "seq_mean_close_vel": null, "seqslope_mean_close_vel": null, "frequency": 2.9087}, {"name": "PD10", "diagnosis": "PD", "event_source": "saved", "has_saved_events": true, "has_complete_events": true, "last_dose_raw": "6h", "time_since_dose_min": 360.0, "levodopa_off": false, "laterality_raw": "L", "laterality_side": "L", "mean_imi": 0.2644, "cv_imi": 0.2255, "seq_imi": 0.079377, "seqslope_imi": -0.008013, "mean_amplitude": 99.5969, "cv_amplitude": 0.2776, "seq_amplitude": 0.565698, "seqslope_amplitude": -0.021976, "mean_rel_amplitude": 1.0228, "cv_rel_amplitude": 0.2603, "seq_rel_amplitude": -0.022416, "seqslope_rel_amplitude": -0.001343, "mean_power": 108882.9595, "cv_power": 0.5106, "seq_power": 0.279395, "seqslope_power": -0.052173, "mean_peak_open_vel": 1009.9784, "cv_peak_open_vel": 0.3603, "seq_peak_open_vel": 0.406179, "seqslope_peak_open_vel": -0.029894, "mean_peak_close_vel": -1232.6956, "cv_peak_close_vel": 0.3922, "seq_peak_close_vel": 0.194261, "seqslope_peak_close_vel": -0.044254, "mean_mean_open_vel": 790.3577, "cv_mean_open_vel": 0.2305, "seq_mean_open_vel": 0.131573, "seqslope_mean_open_vel": -0.007911, "mean_mean_close_vel": -1025.116, "cv_mean_close_vel": 0.2839, "seq_mean_close_vel": 0.256583, "seqslope_mean_close_vel": -0.01653, "frequency": 3.7821}, {"name": "PD14", "diagnosis": "PD", "event_source": "auto", "has_saved_events": false, "has_complete_events": false, "last_dose_raw": null, "time_since_dose_min": null, "levodopa_off": false, "laterality_raw": "L", "laterality_side": "L", "mean_imi": 0.2917, "cv_imi": 0.5701, "seq_imi": 0.03368, "seqslope_imi": -0.048001, "mean_amplitude": 89.5613, "cv_amplitude": 0.3082, "seq_amplitude": 0.55042, "seqslope_amplitude": -0.056591, "mean_rel_amplitude": 1.1461, "cv_rel_amplitude": 0.5883, "seq_rel_amplitude": 0.123626, "seqslope_rel_amplitude": -0.064036, "mean_power": 95525.8246, "cv_power": 0.6384, "seq_power": 0.431693, "seqslope_power": -0.102048, "mean_peak_open_vel": 974.0016, "cv_peak_open_vel": 0.3649, "seq_peak_open_vel": 0.377366, "seqslope_peak_open_vel": -0.045457, "mean_peak_close_vel": -968.1344, "cv_peak_close_vel": 0.3459, "seq_peak_close_vel": 0.38035, "seqslope_peak_close_vel": -0.049501, "mean_mean_open_vel": 879.8587, "cv_mean_open_vel": 0.5825, "seq_mean_open_vel": 0.051719, "seqslope_mean_open_vel": 0.017981, "mean_mean_close_vel": -1108.4189, "cv_mean_close_vel": 0.573, "seq_mean_close_vel": 0.155494, "seqslope_mean_close_vel": -0.0258, "frequency": 3.4282}, {"name": "PD16", "diagnosis": "PD", "event_source": "saved", "has_saved_events": true, "has_complete_events": false, "last_dose_raw": "3.5h", "time_since_dose_min": 210.0, "levodopa_off": false, "laterality_raw": "R", "laterality_side": "R", "mean_imi": 0.4089, "cv_imi": 0.1051, "seq_imi": 0.486029, "seqslope_imi": -0.029363, "mean_amplitude": 76.85, "cv_amplitude": 0.331, "seq_amplitude": 0.839455, "seqslope_amplitude": -0.167458, "mean_rel_amplitude": 0.9339, "cv_rel_amplitude": 0.2793, "seq_rel_amplitude": 0.246214, "seqslope_rel_amplitude": -0.04793, "mean_power": null, "cv_power": null, "seq_power": null, "seqslope_power": null, "mean_peak_open_vel": null, "cv_peak_open_vel": null, "seq_peak_open_vel": null, "seqslope_peak_open_vel": null, "mean_peak_close_vel": null, "cv_peak_close_vel": null, "seq_peak_close_vel": null, "seqslope_peak_close_vel": null, "mean_mean_open_vel": null, "cv_mean_open_vel": null, "seq_mean_open_vel": null, "seqslope_mean_open_vel": null, "mean_mean_close_vel": null, "cv_mean_close_vel": null, "seq_mean_close_vel": null, "seqslope_mean_close_vel": null, "frequency": 2.4456}, {"name": "PSP01", "diagnosis": "PSP", "event_source": "saved", "has_saved_events": true, "has_complete_events": true, "last_dose_raw": "-", "time_since_dose_min": null, "levodopa_off": false, "laterality_raw": "L", "laterality_side": "L", "mean_imi": 0.3795, "cv_imi": 0.0972, "seq_imi": 0.507558, "seqslope_imi": -0.003287, "mean_amplitude": 37.608, "cv_amplitude": 0.2826, "seq_amplitude": 0.749498, "seqslope_amplitude": -0.031314, "mean_rel_amplitude": 0.9963, "cv_rel_amplitude": 0.2031, "seq_rel_amplitude": 0.018243, "seqslope_rel_amplitude": -0.005579, "mean_power": 13492.5469, "cv_power": 0.467, "seq_power": 0.719373, "seqslope_power": -0.066144, "mean_peak_open_vel": 350.4846, "cv_peak_open_vel": 0.2291, "seq_peak_open_vel": 0.599754, "seqslope_peak_open_vel": -0.035805, "mean_peak_close_vel": -431.9662, "cv_peak_close_vel": 0.2504, "seq_peak_close_vel": 0.385459, "seqslope_peak_close_vel": -0.025434, "mean_mean_open_vel": 252.3162, "cv_mean_open_vel": 0.2035, "seq_mean_open_vel": 0.567279, "seqslope_mean_open_vel": -0.022529, "mean_mean_close_vel": -368.4712, "cv_mean_close_vel": 0.1949, "seq_mean_close_vel": 0.070997, "seqslope_mean_close_vel": -0.00785, "frequency": 2.635}, {"name": "PSP02", "diagnosis": "PSP", "event_source": "saved", "has_saved_events": true, "has_complete_events": true, "last_dose_raw": "? (Appt time 2:30 pm)", "time_since_dose_min": null, "levodopa_off": false, "laterality_raw": "R", "laterality_side": "R", "mean_imi": 0.9046, "cv_imi": 0.3469, "seq_imi": 0.306262, "seqslope_imi": -0.049493, "mean_amplitude": 33.7832, "cv_amplitude": 0.5139, "seq_amplitude": 0.436371, "seqslope_amplitude": -0.16534, "mean_rel_amplitude": 1.2871, "cv_rel_amplitude": 0.7947, "seq_rel_amplitude": 0.374753, "seqslope_rel_amplitude": -0.184443, "mean_power": 8916.8768, "cv_power": 0.874, "seq_power": 0.086547, "seqslope_power": -0.281377, "mean_peak_open_vel": 220.8732, "cv_peak_open_vel": 0.6175, "seq_peak_open_vel": 0.087591, "seqslope_peak_open_vel": -0.116037, "mean_peak_close_vel": -273.8671, "cv_peak_close_vel": 0.5997, "seq_peak_close_vel": 0.42415, "seqslope_peak_close_vel": -0.170412, "mean_mean_open_vel": 100.6771, "cv_mean_open_vel": 0.9916, "seq_mean_open_vel": -0.02838, "seqslope_mean_open_vel": -0.014456, "mean_mean_close_vel": -144.021, "cv_mean_close_vel": 0.5336, "seq_mean_close_vel": 0.153535, "seqslope_mean_close_vel": -0.100223, "frequency": 1.1055}, {"name": "PSP04", "diagnosis": "PSP", "event_source": "saved", "has_saved_events": true, "has_complete_events": true, "last_dose_raw": null, "time_since_dose_min": null, "levodopa_off": false, "laterality_raw": "L", "laterality_side": "L", "mean_imi": 0.3062, "cv_imi": 0.3676, "seq_imi": 0.468562, "seqslope_imi": -0.029016, "mean_amplitude": 113.4847, "cv_amplitude": 0.26, "seq_amplitude": 0.760437, "seqslope_amplitude": -0.024053, "mean_rel_amplitude": 0.9844, "cv_rel_amplitude": 0.1146, "seq_rel_amplitude": 0.001649, "seqslope_rel_amplitude": -0.00089, "mean_power": 148561.6703, "cv_power": 0.4829, "seq_power": 0.728928, "seqslope_power": -0.046972, "mean_peak_open_vel": 1232.2417, "cv_peak_open_vel": 0.2676, "seq_peak_open_vel": 0.699045, "seqslope_peak_open_vel": -0.022919, "mean_peak_close_vel": -1405.8375, "cv_peak_close_vel": 0.3081, "seq_peak_close_vel": 0.768362, "seqslope_peak_close_vel": -0.02675, "mean_mean_open_vel": 832.7283, "cv_mean_open_vel": 0.3019, "seq_mean_open_vel": -0.003903, "seqslope_mean_open_vel": 0.006246, "mean_mean_close_vel": -1138.96, "cv_mean_close_vel": 0.323, "seq_mean_close_vel": -0.026045, "seqslope_mean_close_vel": 0.000782, "frequency": 3.2658}], "groups": ["Control", "MSA", "PD", "PSP"]}