{"subjects": [{"name": "Con02", "diagnosis": "Control", "event_source": "saved", "has_saved_events": true, "has_complete_events": true, "last_dose_raw": "-", "time_since_dose_min": null, "levodopa_off": false, "laterality_raw": "R", "laterality_side": "R", "mean_imi": 0.5079, "cv_imi": 0.4244, "seq_imi": 0.007182, "seqslope_imi": 0.003335, "mean_amplitude": 68.621, "cv_amplitude": 0.0887, "seq_amplitude": 0.446102, "seqslope_amplitude": -0.760333, "mean_rel_amplitude": 1.0011, "cv_rel_amplitude": 0.1201, "seq_rel_amplitude": 0.017794, "seqslope_rel_amplitude": -0.002929, "mean_power": 44895.6542, "cv_power": 0.2197, "seq_power": 0.217619, "seqslope_power": -840.243667, "mean_peak_open_vel": 649.8789, "cv_peak_open_vel": 0.1684, "seq_peak_open_vel": 0.065405, "seqslope_peak_open_vel": -5.108684, "mean_peak_close_vel": -887.6325, "cv_peak_close_vel": 0.1508, "seq_peak_close_vel": 0.021513, "seqslope_peak_close_vel": -3.665789, "mean_mean_open_vel": 347.5553, "cv_mean_open_vel": 0.2677, "seq_mean_open_vel": 0.006111, "seqslope_mean_open_vel": -1.32807, "mean_mean_close_vel": -641.2515, "cv_mean_close_vel": 0.2623, "seq_mean_close_vel": 0.045446, "seqslope_mean_close_vel": 6.690175, "frequency": 1.9689}, {"name": "Con03", "diagnosis": "Control", "event_source": "saved", "has_saved_events": true, "has_complete_events": true, "last_dose_raw": null, "time_since_dose_min": null, "levodopa_off": false, "laterality_raw": "L", "laterality_side": "L", "mean_imi": 0.7733, "cv_imi": 0.1163, "seq_imi": 0.148246, "seqslope_imi": -0.006947, "mean_amplitude": 113.1743, "cv_amplitude": 0.1571, "seq_amplitude": 0.380844, "seqslope_amplitude": -2.074421, "mean_rel_amplitude": 1.0265, "cv_rel_amplitude": 0.2933, "seq_rel_amplitude": 1e-06, "seqslope_rel_amplitude": 5.8e-05, "mean_power": 127275.7324, "cv_power": 0.3, "seq_power": 0.306064, "seqslope_power": -4008.756737, "mean_peak_open_vel": 1097.0571, "cv_peak_open_vel": 0.2169, "seq_peak_open_vel": 0.201048, "seqslope_peak_open_vel": -20.24, "mean_peak_close_vel": -1186.3857, "cv_peak_close_vel": 0.3396, "seq_peak_close_vel": 0.284395, "seqslope_peak_close_vel": -41.139211, "mean_mean_open_vel": 490.7533, "cv_mean_open_vel": 0.1467, "seq_mean_open_vel": 0.002294, "seqslope_mean_open_vel": -0.593912, "mean_mean_close_vel": -621.7224, "cv_mean_close_vel": 0.2977, "seq_mean_close_vel": 0.013178, "seqslope_mean_close_vel": -4.000877, "frequency": 1.2932}, {"name": "Con04", "diagnosis": "Control", "event_source": "auto", "has_saved_events": false, "has_complete_events": false, "last_dose_raw": "30m", "time_since_dose_min": 30.0, "levodopa_off": false, "laterality_raw": null, "laterality_side": null, "mean_imi": 0.4053, "cv_imi": 0.4884, "seq_imi": 0.325185, "seqslope_imi": -0.036656, "mean_amplitude": 119.6648, "cv_amplitude": 0.2162, "seq_amplitude": 0.517776, "seqslope_amplitude": -6.690315, "mean_rel_amplitude": 1.049, "cv_rel_amplitude": 0.311, "seq_rel_amplitude": 0.12225, "seqslope_rel_amplitude": -0.022467, "mean_power": 1974179.141, "cv_power": 2.4217, "seq_power": 0.17108, "seqslope_power": -690941.994124, "mean_peak_open_vel": 14016.5714, "cv_peak_open_vel": 2.3053, "seq_peak_open_vel": 0.160493, "seqslope_peak_open_vel": -4405.252761, "mean_peak_close_vel": -5896.6429, "cv_peak_close_vel": 3.0061, "seq_peak_close_vel": 0.195392, "seqslope_peak_close_vel": -2450.836616, "mean_mean_open_vel": 1146.3936, "cv_mean_open_vel": 1.5642, "seq_mean_open_vel": 0.110205, "seqslope_mean_open_vel": -5.420338, "mean_mean_close_vel": -970.5052, "cv_mean_close_vel": 0.6026, "seq_mean_close_vel": 0.209376, "seqslope_mean_close_vel": -60.937885, "frequency": 2.4673}, {"name": "Con05", "diagnosis": "Control", "event_source": "saved", "has_saved_events": true, "has_complete_events": true, "last_dose_raw": null, "time_since_dose_min": null, "levodopa_off": true, "laterality_raw": "L", "laterality_side": "L", "mean_imi": 0.7372, "cv_imi": 0.5356, "seq_imi": 0.220511, "seqslope_imi": -0.061664, "mean_amplitude": 94.5636, "cv_amplitude": 0.1672, "seq_amplitude": 0.926396, "seqslope_amplitude": -4.396154, "mean_rel_amplitude": 0.9967, "cv_rel_amplitude": 0.2419, "seq_rel_amplitude": 0.367365, "seqslope_rel_amplitude": -0.011462, "mean_power": 57594.1377, "cv_power": 0.4429, "seq_power": 0.606911, "seqslope_power": -6658.177727, "mean_peak_open_vel": 597.0231, "cv_peak_open_vel": 0.3629, "seq_peak_open_vel": 0.385564, "seqslope_peak_open_vel": -45.733636, "mean_peak_close_vel": -931.8321, "cv_peak_close_vel": 0.3406, "seq_peak_close_vel": 0.037156, "seqslope_peak_close_vel": -16.98042, "mean_mean_open_vel": 303.01, "cv_mean_open_vel": 0.3722, "seq_mean_open_vel": 0.000192, "seqslope_mean_open_vel": -0.463182, "mean_mean_close_vel": -469.3529, "cv_mean_close_vel": 0.6265, "seq_mean_close_vel": 0.20107, "seqslope_mean_close_vel": -34.146503, "frequency": 1.3565}, {"name": "Con07", "diagnosis": "Control", "event_source": "saved", "has_saved_events": true, "has_complete_events": true, "last_dose_raw": null, "time_since_dose_min": null, "levodopa_off": false, "laterality_raw": null, "laterality_side": null, "mean_imi": 0.3008, "cv_imi": 0.0692, "seq_imi": 0.196524, "seqslope_imi": 0.000562, "mean_amplitude": 132.6452, "cv_amplitude": 0.0755, "seq_amplitude": 0.634328, "seqslope_amplitude": -2.391083, "mean_rel_amplitude": 0.9996, "cv_rel_amplitude": 0.0956, "seq_rel_amplitude": 0.059624, "seqslope_rel_amplitude": -0.010895, "mean_power": 243243.1326, "cv_power": 0.8149, "seq_power": 0.282681, "seqslope_power": -13428.238784, "mean_peak_open_vel": 1833.1536, "cv_peak_open_vel": 0.8386, "seq_peak_open_vel": 0.267384, "seqslope_peak_open_vel": -70.135623, "mean_peak_close_vel": -16759.925, "cv_peak_close_vel": 2.6123, "seq_peak_close_vel": 0.061025, "seqslope_peak_close_vel": -1789.971459, "mean_mean_open_vel": 982.3705, "cv_mean_open_vel": 0.1391, "seq_mean_open_vel": 0.211357, "seqslope_mean_open_vel": -22.857853, "mean_mean_close_vel": -1170.2445, "cv_mean_close_vel": 0.1444, "seq_mean_close_vel": 0.164223, "seqslope_mean_close_vel": -3.874856, "frequency": 3.3245}, {"name": "Con08", "diagnosis": "Control", "event_source": "saved", "has_saved_events": true, "has_complete_events": true, "last_dose_raw": null, "time_since_dose_min": null, "levodopa_off": false, "laterality_raw": "L", "laterality_side": "L", "mean_imi": 0.3458, "cv_imi": 0.0592, "seq_imi": 4.3e-05, "seqslope_imi": -1.1e-05, "mean_amplitude": 177.8258, "cv_amplitude": 0.0673, "seq_amplitude": 0.624201, "seqslope_amplitude": -0.820983, "mean_rel_amplitude": 0.9975, "cv_rel_amplitude": 0.0706, "seq_rel_amplitude": 0.01717, "seqslope_rel_amplitude": -0.000714, "mean_power": 287874.2529, "cv_power": 0.208, "seq_power": 0.797715, "seqslope_power": -4478.171508, "mean_peak_open_vel": 1607.0233, "cv_peak_open_vel": 0.1569, "seq_peak_open_vel": 0.773757, "seqslope_peak_open_vel": -17.944897, "mean_peak_close_vel": -2435.8767, "cv_peak_close_vel": 0.0722, "seq_peak_close_vel": 0.540038, "seqslope_peak_close_vel": -10.476923, "mean_mean_open_vel": 1036.2249, "cv_mean_open_vel": 0.1155, "seq_mean_open_vel": 0.121972, "seqslope_mean_open_vel": -3.645295, "mean_mean_close_vel": -1387.4207, "cv_mean_close_vel": 0.2463, "seq_mean_close_vel": 0.002124, "seqslope_mean_close_vel": 1.368413, "frequency": 2.8918}, {"name": "Con09", "diagnosis": "Control", "event_source": "saved", "has_saved_events": true, "has_complete_events": false, "last_dose_raw": null, "time_since_dose_min": null, "levodopa_off": false, "laterality_raw": "R", "laterality_side": "R", "mean_imi": 0.2503, "cv_imi": 0.1544, "seq_imi": 0.420708, "seqslope_imi": -0.008131, "mean_amplitude": 124.3856, "cv_amplitude": 0.2313, "seq_amplitude": 0.551213, "seqslope_amplitude": -8.947364, "mean_rel_amplitude": 1.1943, "cv_rel_amplitude": 1.2102, "seq_rel_amplitude": 0.116103, "seqslope_rel_amplitude": -0.035197, "mean_power": null, "cv_power": null, "seq_power": null, "seqslope_power": null, "mean_peak_open_vel": null, "cv_peak_open_vel": null, "seq_peak_open_vel": null, "seqslope_peak_open_vel": null, "mean_peak_close_vel": null, "cv_peak_close_vel": null, "seq_peak_close_vel": null, "seqslope_peak_close_vel": null, "mean_mean_open_vel": null, "cv_mean_open_vel": null, "seq_mean_open_vel": null, "seqslope_mean_open_vel": null, "mean_mean_close_vel": null, "cv_mean_close_vel": null, "seq_mean_close_vel": null, "seqslope_mean_close_vel": null, "frequency": 3.9952}, {"name": "MSA01", "diagnosis": "MSA", "event_source": "saved", "has_saved_events": true, "has_complete_events": true, "last_dose_raw": null, "time_since_dose_min": null, "levodopa_off": false, "laterality_raw": "L", "laterality_side": "L", "mean_imi": 0.6804, "cv_imi": 0.1943, "seq_imi": 0.050498, "seqslope_imi": -0.004479, "mean_amplitude": 65.315, "cv_amplitude": 0.2946, "seq_amplitude": 0.36967, "seqslope_amplitude": -1.689913, "mean_rel_amplitude": 1.1059, "cv_rel_amplitude": 0.6237, "seq_rel_amplitude": 0.004955, "seqslope_rel_amplitude": 0.00732, "mean_power": 35380.9175, "cv_power": 0.4084, "seq_power": 0.143902, "seqslope_power": -791.794287, "mean_peak_open_vel": 525.9562, "cv_peak_open_vel": 0.2462, "seq_peak_open_vel": 0.000675, "seqslope_peak_open_vel": 0.485935, "mean_peak_close_vel": -579.05, "cv_peak_close_vel": 0.2872, "seq_peak_close_vel": 0.279263, "seqslope_peak_close_vel": -12.695609, "mean_mean_open_vel": 269.5213, "cv_mean_open_vel": 0.3146, "seq_mean_open_vel": 0.002291, "seqslope_mean_open_vel": 0.5863, "mean_mean_close_vel": -275.8512, "cv_mean_close_vel": 0.3337, "seq_mean_close_vel": 0.318642, "seqslope_mean_close_vel": -7.50737, "frequency": 1.4697}, {"name": "MSA02", "diagnosis": "MSA", "event_source": "saved", "has_saved_events": true, "has_complete_events": true, "last_dose_raw": null, "time_since_dose_min": null, "levodopa_off": true, "laterality_raw": "R", "laterality_side": "R", "mean_imi": 0.3124, "cv_imi": 0.0808, "seq_imi": 0.023971, "seqslope_imi": 0.000556, "mean_amplitude": 134.4603, "cv_amplitude": 0.1151, "seq_amplitude": 0.590372, "seqslope_amplitude": -2.266163, "mean_rel_amplitude": 1.0035, "cv_rel_amplitude": 0.1181, "seq_rel_amplitude": 0.041133, "seqslope_rel_amplitude": -0.008396, "mean_power": 207869.9949, "cv_power": 0.2542, "seq_power": 0.422526, "seqslope_power": -4775.173426, "mean_peak_open_vel": 1527.3051, "cv_peak_open_vel": 0.1582, "seq_peak_open_vel": 0.257396, "seqslope_peak_open_vel": -10.671034, "mean_peak_close_vel": -1636.5127, "cv_peak_close_vel": 0.1649, "seq_peak_close_vel": 0.268885, "seqslope_peak_close_vel": -38.200456, "mean_mean_open_vel": 1000.7495, "cv_mean_open_vel": 0.2272, "seq_mean_open_vel": 0.333183, "seqslope_mean_open_vel": -11.706143, "mean_mean_close_vel": -1117.0259, "cv_mean_close_vel": 0.1896, "seq_mean_close_vel": 0.13526, "seqslope_mean_close_vel": -18.463539, "frequency": 3.201}, {"name": "MSA03", "diagnosis": "MSA", "event_source": "auto", "has_saved_events": false, "has_complete_events": false, "last_dose_raw": null, "time_since_dose_min": null, "levodopa_off": false, "laterality_raw": "L", "laterality_side": "L", "mean_imi": 0.5435, "cv_imi": 0.3425, "seq_imi": 0.33248, "seqslope_imi": -0.040288, "mean_amplitude": 114.2514, "cv_amplitude": 0.2048, "seq_amplitude": 0.535038, "seqslope_amplitude": -9.066998, "mean_rel_amplitude": 1.0995, "cv_rel_amplitude": 0.4719, "seq_rel_amplitude": 0.119145, "seqslope_rel_amplitude": -0.036024, "mean_power": 124109.9873, "cv_power": 0.4724, "seq_power": 0.355478, "seqslope_power": -18035.220156, "mean_peak_open_vel": 1045.9095, "cv_peak_open_vel": 0.3704, "seq_peak_open_vel": 0.290746, "seqslope_peak_open_vel": -78.757585, "mean_peak_close_vel": -1108.0622, "cv_peak_close_vel": 0.3158, "seq_peak_close_vel": 0.14745, "seqslope_peak_close_vel": -41.38996, "mean_mean_open_vel": 671.9795, "cv_mean_open_vel": 1.5654, "seq_mean_open_vel": 0.274929, "seqslope_mean_open_vel": 1.901557, "mean_mean_close_vel": -770.0524, "cv_mean_close_vel": 0.8925, "seq_mean_close_vel": 0.187231, "seqslope_mean_close_vel": 94.450753, "frequency": 1.8399}, {"name": "MSA04", "diagnosis": "MSA", "event_source": "saved", "has_saved_events": true, "has_complete_events": true, "last_dose_raw": null, "time_since_dose_min": null, "levodopa_off": false, "laterality_raw": "L", "laterality_side": "L", "mean_imi": 0.2344, "cv_imi": 0.317, "seq_imi": 0.383445, "seqslope_imi": -0.002124, "mean_amplitude": 80.6532, "cv_amplitude": 0.5786, "seq_amplitude": 0.666949, "seqslope_amplitude": -1.729491, "mean_rel_amplitude": 1.7789, "cv_rel_amplitude": 2.8637, "seq_rel_amplitude": 0.015682, "seqslope_rel_amplitude": 0.02942, "mean_power": 101283.7882, "cv_power": 0.8986, "seq_power": 0.575071, "seqslope_power": -3125.22017, "mean_peak_open_vel": 948.0266, "cv_peak_open_vel": 0.6162, "seq_peak_open_vel": 0.570867, "seqslope_peak_open_vel": -20.048795, "mean_peak_close_vel": -1009.9975, "cv_peak_close_vel": 0.6372, "seq_peak_close_vel": 0.60047, "seqslope_peak_close_vel": -22.65517, "mean_mean_open_vel": 875.6723, "cv_mean_open_vel": 0.6368, "seq_mean_open_vel": 0.401917, "seqslope_mean_open_vel": -16.021057, "mean_mean_close_vel": -957.1947, "cv_mean_close_vel": 0.5695, "seq_mean_close_vel": 0.321034, "seqslope_mean_close_vel": -14.026658, "frequency": 4.2662}, {"name": "MSA05", "diagnosis": "MSA", "event_source": "saved", "has_saved_events": true, "has_complete_events": true, "last_dose_raw": null, "time_since_dose_min": null, "levodopa_off": true, "laterality_raw": "L", "laterality_side": "L", "mean_imi": 0.2649, "cv_imi": 0.1824, "seq_imi": 0.093346, "seqslope_imi": -0.003081, "mean_amplitude": 123.9586, "cv_amplitude": 0.2117, "seq_amplitude": 0.492769, "seqslope_amplitude": -1.894387, "mean_rel_amplitude": 1.0172, "cv_rel_amplitude": 0.1808, "seq_rel_amplitude": 0.02842, "seqslope_rel_amplitude": -0.005574, "mean_power": 196918.8009, "cv_power": 0.3998, "seq_power": 0.479541, "seqslope_power": -5504.95515, "mean_peak_open_vel": 1535.6182, "cv_peak_open_vel": 0.2235, "seq_peak_open_vel": 0.413035, "seqslope_peak_open_vel": -18.838829, "mean_peak_close_vel": -1572.5523, "cv_peak_close_vel": 0.2279, "seq_peak_close_vel": 0.492951, "seqslope_peak_close_vel": -20.766866, "mean_mean_open_vel": 1259.5705, "cv_mean_open_vel": 0.1739, "seq_mean_open_vel": 0.274559, "seqslope_mean_open_vel": -12.74737, "mean_mean_close_vel": -1314.2114, "cv_mean_close_vel": 0.2242, "seq_mean_close_vel": 0.248657, "seqslope_mean_close_vel": -10.812313, "frequency": 3.775}, {"name": "MSA06", "diagnosis": "MSA", "event_source": "saved", "has_saved_events": true, "has_complete_events": true, "last_dose_raw": null, "time_since_dose_min": null, "levodopa_off": true, "laterality_raw": "L", "laterality_side": "L", "mean_imi": 0.486, "cv_imi": 0.4917, "seq_imi": 0.077149, "seqslope_imi": -0.008682, "mean_amplitude": 73.2132, "cv_amplitude": 0.4116, "seq_amplitude": 0.441341, "seqslope_amplitude": -3.755025, "mean_rel_amplitude": 1.2668, "cv_rel_amplitude": 0.9444, "seq_rel_amplitude": 0.001639, "seqslope_rel_amplitude": -0.004446, "mean_power": 46818.3374, "cv_power": 0.639, "seq_power": 0.531947, "seqslope_power": -5722.142398, "mean_peak_open_vel": 590.4174, "cv_peak_open_vel": 0.3753, "seq_peak_open_vel": 0.62143, "seqslope_peak_open_vel": -45.76131, "mean_peak_close_vel": -646.3773, "cv_peak_close_vel": 0.4005, "seq_peak_close_vel": 0.550732, "seqslope_peak_close_vel": -48.768696, "mean_mean_open_vel": 388.6814, "cv_mean_open_vel": 0.4155, "seq_mean_open_vel": 0.441824, "seqslope_mean_open_vel": -16.308613, "mean_mean_close_vel": -439.4407, "cv_mean_close_vel": 0.3551, "seq_mean_close_vel": 0.42532, "seqslope_mean_close_vel": -15.990578, "frequency": 2.0576}, {"name": "MSA07", "diagnosis": "MSA", "event_source": "auto", "has_saved_events": false, "has_complete_events": false, "last_dose_raw": null, "time_since_dose_min": null, "levodopa_off": true, "laterality_raw": "R", "laterality_side": "R", "mean_imi": 0.5519, "cv_imi": 1.5747, "seq_imi": 0.115116, "seqslope_imi": -0.033138, "mean_amplitude": 17.2469, "cv_amplitude": 0.1983, "seq_amplitude": 0.495452, "seqslope_amplitude": -0.642219, "mean_rel_amplitude": 1.0422, "cv_rel_amplitude": 0.2474, "seq_rel_amplitude": 0.155191, "seqslope_rel_amplitude": -0.04447, "mean_power": 1770.7967, "cv_power": 0.4729, "seq_power": 0.269105, "seqslope_power": -163.958571, "mean_peak_open_vel": 101.75, "cv_peak_open_vel": 0.3764, "seq_peak_open_vel": 0.173722, "seqslope_peak_open_vel": -6.100857, "mean_peak_close_vel": -111.0708, "cv_peak_close_vel": 0.4255, "seq_peak_close_vel": 0.07183, "seqslope_peak_close_vel": -1.689429, "mean_mean_open_vel": 181.6192, "cv_mean_open_vel": 0.9411, "seq_mean_open_vel": 0.130042, "seqslope_mean_open_vel": -24.040629, "mean_mean_close_vel": -186.5836, "cv_mean_close_vel": 0.8637, "seq_mean_close_vel": 0.213262, "seqslope_mean_close_vel": 18.01519, "frequency": 1.8119}, {"name": "MSA08", "diagnosis": "MSA", "event_source": "saved", "has_saved_events": true, "has_complete_events": true, "last_dose_raw": "10am appt", "time_since_dose_min": null, "levodopa_off": false, "laterality_raw": "R", "laterality_side": "R", "mean_imi": 0.6772, "cv_imi": 0.133, "seq_imi": 0.28429, "seqslope_imi": -0.014088, "mean_amplitude": 111.8864, "cv_amplitude": 0.2645, "seq_amplitude": 0.623507, "seqslope_amplitude": -10.64612, "mean_rel_amplitude": 1.0525, "cv_rel_amplitude": 0.3171, "seq_rel_amplitude": 0.055412, "seqslope_rel_amplitude": -0.024751, "mean_power": 75630.4154, "cv_power": 0.4062, "seq_power": 0.503991, "seqslope_power": -10102.195376, "mean_peak_open_vel": 655.0339, "cv_peak_open_vel": 0.2301, "seq_peak_open_vel": 0.24334, "seqslope_peak_open_vel": -32.974125, "mean_peak_close_vel": -723.1018, "cv_peak_close_vel": 0.2938, "seq_peak_close_vel": 0.476189, "seqslope_peak_close_vel": -54.854255, "mean_mean_open_vel": 375.4554, "cv_mean_open_vel": 0.2746, "seq_mean_open_vel": 0.662988, "seqslope_mean_open_vel": -36.064438, "mean_mean_close_vel": -400.3321, "cv_mean_close_vel": 0.267, "seq_mean_close_vel": 0.335983, "seqslope_mean_close_vel": -26.533838, "frequency": 1.4767}, {"name": "MSA09", "diagnosis": "MSA", "event_source": "saved", "has_saved_events": true, "has_complete_events": true, "last_dose_raw": "12:30 appt", "time_since_dose_min": null, "levodopa_off": false, "laterality_raw": "L", "laterality_side": "L", "mean_imi": 1.2036, "cv_imi": 0.214, "seq_imi": null, "seqslope_imi": null, "mean_amplitude": 82.2527, "cv_amplitude": 0.2692, "seq_amplitude": null, "seqslope_amplitude": null, "mean_rel_amplitude": 0.9255, "cv_rel_amplitude": 0.2325, "seq_rel_amplitude": null, "seqslope_rel_amplitude": null, "mean_power": 22646.6518, "cv_power": 0.6146, "seq_power": null, "seqslope_power": null, "mean_peak_open_vel": 255.7091, "cv_peak_open_vel": 0.313, "seq_peak_open_vel": null, "seqslope_peak_open_vel": null, "mean_peak_close_vel": -455.4682, "cv_peak_close_vel": 0.5181, "seq_peak_close_vel": null, "seqslope_peak_close_vel": null, "mean_mean_open_vel": 137.5309, "cv_mean_open_vel": 0.3867, "seq_mean_open_vel": null, "seqslope_mean_open_vel": null, "mean_mean_close_vel": -240.6782, "cv_mean_close_vel": 0.512, "seq_mean_close_vel": null, "seqslope_mean_close_vel": null, "frequency": 0.8308}, {"name": "MSA10", "diagnosis": "MSA", "event_source": "saved", "has_saved_events": true, "has_complete_events": true, "last_dose_raw": "-", "time_since_dose_min": null, "levodopa_off": true, "laterality_raw": "L", "laterality_side": "L", "mean_imi": 0.2449, "cv_imi": 0.1728, "seq_imi": 0.440607, "seqslope_imi": -0.003269, "mean_amplitude": 109.4729, "cv_amplitude": 0.2599, "seq_amplitude": 0.541161, "seqslope_amplitude": -3.355792, "mean_rel_amplitude": 1.0233, "cv_rel_amplitude": 0.2685, "seq_rel_amplitude": 0.015895, "seqslope_rel_amplitude": -0.006723, "mean_power": 158261.135, "cv_power": 0.5189, "seq_power": 0.522631, "seqslope_power": -9345.422096, "mean_peak_open_vel": 1364.1221, "cv_peak_open_vel": 0.2469, "seq_peak_open_vel": 0.387726, "seqslope_peak_open_vel": -36.016226, "mean_peak_close_vel": -1455.1147, "cv_peak_close_vel": 0.2525, "seq_peak_close_vel": 0.46781, "seqslope_peak_close_vel": -37.478288, "mean_mean_open_vel": 1121.6462, "cv_mean_open_vel": 0.1664, "seq_mean_open_vel": 0.282204, "seqslope_mean_open_vel": -23.305103, "mean_mean_close_vel": -1169.0071, "cv_mean_close_vel": 0.1866, "seq_mean_close_vel": 0.454215, "seqslope_mean_close_vel": -36.192234, "frequency": 4.0833}, {"name": "MSA12", "diagnosis": "MSA", "event_source": "saved", "has_saved_events": true, "has_complete_events": true, "last_dose_raw": "10am appt", "time_since_dose_min": null, "levodopa_off": false, "laterality_raw": "R", "laterality_side": "R", "mean_imi": 0.5794, "cv_imi": 0.1464, "seq_imi": 0.211692, "seqslope_imi": -0.004629, "mean_amplitude": 141.8814, "cv_amplitude": 0.0625, "seq_amplitude": 0.63448, "seqslope_amplitude": -2.405741, "mean_rel_amplitude": 1.0093, "cv_rel_amplitude": 0.081, "seq_rel_amplitude": 0.049907, "seqslope_rel_amplitude": -0.005957, "mean_power": 165159.7471, "cv_power": 0.1874, "seq_power": 0.392498, "seqslope_power": -4776.983955, "mean_peak_open_vel": 1160.8543, "cv_peak_open_vel": 0.1598, "seq_peak_open_vel": 0.289313, "seqslope_peak_open_vel": -14.199802, "mean_peak_close_vel": -1215.96, "cv_peak_close_vel": 0.1547, "seq_peak_close_vel": 0.174036, "seqslope_peak_close_vel": -4.069048, "mean_mean_open_vel": 518.8063, "cv_mean_open_vel": 0.1466, "seq_mean_open_vel": 0.175848, "seqslope_mean_open_vel": -3.462235, "mean_mean_close_vel": -556.8809, "cv_mean_close_vel": 0.301, "seq_mean_close_vel": 0.185682, "seqslope_mean_close_vel": -8.16754, "frequency": 1.7259}, {"name": "PD02", "diagnosis": "PD", "event_source": "saved", "has_saved_events": true, "has_complete_events": true, "last_dose_raw": "5h", "time_since_dose_min": 300.0, "levodopa_off": false, "laterality_raw": "R", "laterality_side": "R", "mean_imi": 0.2917, "cv_imi": 0.1118, "seq_imi": 0.103335, "seqslope_imi": -0.003158, "mean_amplitude": 90.9251, "cv_amplitude": 0.1187, "seq_amplitude": 0.741439, "seqslope_amplitude": -2.970358, "mean_rel_amplitude": 1.0021, "cv_rel_amplitude": 0.1193, "seq_rel_amplitude": 0.073071, "seqslope_rel_amplitude": -0.00844, "mean_power": 96598.3213, "cv_power": 0.2731, "seq_power": 0.671517, "seqslope_power": -6562.328254, "mean_peak_open_vel": 1048.4038, "cv_peak_open_vel": 0.1812, "seq_peak_open_vel": 0.459222, "seqslope_peak_open_vel": -36.668419, "mean_peak_close_vel": -1268.3462, "cv_peak_close_vel": 0.137, "seq_peak_close_vel": 0.642152, "seqslope_peak_close_vel": -43.723568, "mean_mean_open_vel": 724.4341, "cv_mean_open_vel": 0.2012, "seq_mean_open_vel": 0.150925, "seqslope_mean_open_vel": -15.253802, "mean_mean_close_vel": -1029.8141, "cv_mean_close_vel": 0.1851, "seq_mean_close_vel": 0.11623, "seqslope_mean_close_vel": -21.790134, "frequency": 3.4282}, {"name": "PD03", "diagnosis": "PD", "event_source": "saved", "has_saved_events": true, "has_complete_events": true, "last_dose_raw": "2h", "time_since_dose_min": 120.0, "levodopa_off": false, "laterality_raw": "L", "laterality_side": "L", "mean_imi": 0.3118, "cv_imi": 0.1407, "seq_imi": 0.178105, "seqslope_imi": 0.000675, "mean_amplitude": 109.5807, "cv_amplitude": 0.1322, "seq_amplitude": 0.463579, "seqslope_amplitude": -3.30348, "mean_rel_amplitude": 1.0178, "cv_rel_amplitude": 0.2124, "seq_rel_amplitude": 0.130167, "seqslope_rel_amplitude": -0.0197, "mean_power": 118891.1895, "cv_power": 0.3144, "seq_power": 0.598582, "seqslope_power": -6938.858128, "mean_peak_open_vel": 1066.8937, "cv_peak_open_vel": 0.2283, "seq_peak_open_vel": 0.587036, "seqslope_peak_open_vel": -36.310702, "mean_peak_close_vel": -1445.6116, "cv_peak_close_vel": 0.1585, "seq_peak_close_vel": 0.354749, "seqslope_peak_close_vel": -42.262563, "mean_mean_open_vel": 760.7932, "cv_mean_open_vel": 0.222, "seq_mean_open_vel": 0.410871, "seqslope_mean_open_vel": -16.100802, "mean_mean_close_vel": -1251.5996, "cv_mean_close_vel": 0.1243, "seq_mean_close_vel": 0.329807, "seqslope_mean_close_vel": -27.547932, "frequency": 3.2072}, {"name": "PD04", "diagnosis": "PD", "event_source": "saved", "has_saved_events": true, "has_complete_events": false, "last_dose_raw": "6h", "time_since_dose_min": 360.0, "levodopa_off": false, "laterality_raw": "R", "laterality_side": "R", "mean_imi": 0.4921, "cv_imi": 0.2014, "seq_imi": 0.030295, "seqslope_imi": 0.001141, "mean_amplitude": 97.5524, "cv_amplitude": 0.2164, "seq_amplitude": 0.659815, "seqslope_amplitude": -3.352141, "mean_rel_amplitude": 1.0053, "cv_rel_amplitude": 0.1701, "seq_rel_amplitude": 0.008608, "seqslope_rel_amplitude": -0.004722, "mean_power": null, "cv_power": null, "seq_power": null, "seqslope_power": null, "mean_peak_open_vel": null, "cv_peak_open_vel": null, "seq_peak_open_vel": null, "seqslope_peak_open_vel": null, "mean_peak_close_vel": null, "cv_peak_close_vel": null, "seq_peak_close_vel": null, "seqslope_peak_close_vel": null, "mean_mean_open_vel": null, "cv_mean_open_vel": null, "seq_mean_open_vel": null, "seqslope_mean_open_vel": null, "mean_mean_close_vel": null, "cv_mean_close_vel": null, "seq_mean_close_vel": null, "seqslope_mean_close_vel": null, "frequency": 2.0321}, {"name": "PD05", "diagnosis": "PD", "event_source": "saved", "has_saved_events": true, "has_complete_events": true, "last_dose_raw": "-", "time_since_dose_min": null, "levodopa_off": true, "laterality_raw": "L", "laterality_side": "L", "mean_imi": 0.7227, "cv_imi": 0.1079, "seq_imi": 0.363458, "seqslope_imi": -0.03333, "mean_amplitude": 140.3875, "cv_amplitude": 0.0501, "seq_amplitude": 0.545205, "seqslope_amplitude": -3.838, "mean_rel_amplitude": 0.9973, "cv_rel_amplitude": 0.0727, "seq_rel_amplitude": 0.657636, "seqslope_rel_amplitude": -0.03034, "mean_power": 120742.9083, "cv_power": 0.2357, "seq_power": 0.640706, "seqslope_power": -14539.348, "mean_peak_open_vel": 859.125, "cv_peak_open_vel": 0.2233, "seq_peak_open_vel": 0.400034, "seqslope_peak_open_vel": -77.04, "mean_peak_close_vel": -1328.6375, "cv_peak_close_vel": 0.1343, "seq_peak_close_vel": 0.009131, "seqslope_peak_close_vel": 7.71, "mean_mean_open_vel": 422.4233, "cv_mean_open_vel": 0.205, "seq_mean_open_vel": 0.31266, "seqslope_mean_open_vel": 19.589, "mean_mean_close_vel": -554.1225, "cv_mean_close_vel": 0.2743, "seq_mean_close_vel": 0.752307, "seqslope_mean_close_vel": -123.27, "frequency": 1.3837}, {"name": "PD06", "diagnosis": "PD", "event_source": "saved", "has_saved_events": true, "has_complete_events": true, "last_dose_raw": "6h", "time_since_dose_min": 360.0, "levodopa_off": false, "laterality_raw": "R", "laterality_side": "R", "mean_imi": 0.3417, "cv_imi": 0.0845, "seq_imi": 0.090324, "seqslope_imi": 0.00501, "mean_amplitude": 112.3, "cv_amplitude": 0.1118, "seq_amplitude": 0.739967, "seqslope_amplitude": -7.569429, "mean_rel_amplitude": 0.9661, "cv_rel_amplitude": 0.0824, "seq_rel_amplitude": 0.454742, "seqslope_rel_amplitude": 0.03643, "mean_power": 150579.9462, "cv_power": 0.0879, "seq_power": 0.920077, "seqslope_power": -6244.876, "mean_peak_open_vel": 1391.5687, "cv_peak_open_vel": 0.0748, "seq_peak_open_vel": 0.072331, "seqslope_peak_open_vel": -10.305, "mean_peak_close_vel": -1376.9167, "cv_peak_close_vel": 0.1378, "seq_peak_close_vel": 0.772062, "seqslope_peak_close_vel": -107.991429, "mean_mean_open_vel": 1038.1125, "cv_mean_open_vel": 0.2321, "seq_mean_open_vel": 0.112396, "seqslope_mean_open_vel": -8.708, "mean_mean_close_vel": -747.5967, "cv_mean_close_vel": 0.2967, "seq_mean_close_vel": 0.746661, "seqslope_mean_close_vel": -109.955714, "frequency": 2.9265}, {"name": "PD07", "diagnosis": "PD", "event_source": "saved", "has_saved_events": true, "has_complete_events": true, "last_dose_raw": "-", "time_since_dose_min": null, "levodopa_off": true, "laterality_raw": "L", "laterality_side": "L", "mean_imi": 0.3006, "cv_imi": 0.3572, "seq_imi": 0.60926, "seqslope_imi": -0.03255, "mean_amplitude": 57.1664, "cv_amplitude": 0.2447, "seq_amplitude": 0.824727, "seqslope_amplitude": -5.535312, "mean_rel_amplitude": 1.0684, "cv_rel_amplitude": 0.4313, "seq_rel_amplitude": 0.172518, "seqslope_rel_amplitude": -0.034709, "mean_power": 31554.1732, "cv_power": 0.4106, "seq_power": 0.792682, "seqslope_power": -5412.713313, "mean_peak_open_vel": 529.0661, "cv_peak_open_vel": 0.2466, "seq_peak_open_vel": 0.571996, "seqslope_peak_open_vel": -44.305312, "mean_peak_close_vel": -670.4143, "cv_peak_close_vel": 0.3425, "seq_peak_close_vel": 0.563895, "seqslope_peak_close_vel": -80.090156, "mean_mean_open_vel": 464.4318, "cv_mean_open_vel": 0.2964, "seq_mean_open_vel": 0.239623, "seqslope_mean_open_vel": 28.888625, "mean_mean_close_vel": -790.5146, "cv_mean_close_vel": 0.3447, "seq_mean_close_vel": 0.056894, "seqslope_mean_close_vel": -28.674781, "frequency": 3.3267}, {"name": "PD08", "diagnosis": "PD", "event_source": "saved", "has_saved_events": true, "has_complete_events": true, "last_dose_raw": "1h 30m", "time_since_dose_min": 90.0, "levodopa_off": false, "laterality_raw": "L", "laterality_side": "L", "mean_imi": 0.2557, "cv_imi": 0.0984, "seq_imi": 0.216944, "seqslope_imi": -0.00185, "mean_amplitude": 89.7941, "cv_amplitude": 0.1927, "seq_amplitude": 0.649757, "seqslope_amplitude": -2.578823, "mean_rel_amplitude": 1.0071, "cv_rel_amplitude": 0.2131, "seq_rel_amplitude": 0.074392, "seqslope_rel_amplitude": -0.007628, "mean_power": 99643.6303, "cv_power": 0.3923, "seq_power": 0.75317, "seqslope_power": -5646.670492, "mean_peak_open_vel": 1071.1538, "cv_peak_open_vel": 0.2384, "seq_peak_open_vel": 0.6869, "seqslope_peak_open_vel": -30.162449, "mean_peak_close_vel": -1178.9115, "cv_peak_close_vel": 0.2311, "seq_peak_close_vel": 0.574867, "seqslope_peak_close_vel": -34.957235, "mean_mean_open_vel": 890.4179, "cv_mean_open_vel": 0.1791, "seq_mean_open_vel": 0.307844, "seqslope_mean_open_vel": -9.157022, "mean_mean_close_vel": -1075.0392, "cv_mean_close_vel": 0.2928, "seq_mean_close_vel": 0.233472, "seqslope_mean_close_vel": -23.82541, "frequency": 3.9108}, {"name": "PD09", "diagnosis": "PD", "event_source": "saved", "has_saved_events": true, "has_complete_events": true, "last_dose_raw": "45m", "time_since_dose_min": 45.0, "levodopa_off": false, "laterality_raw": "L", "laterality_side": "L", "mean_imi": 0.3438, "cv_imi": 0.0615, "seq_imi": 0.251415, "seqslope_imi": -0.005155, "mean_amplitude": 156.3053, "cv_amplitude": 0.0261, "seq_amplitude": 0.825478, "seqslope_amplitude": -2.002024, "mean_rel_amplitude": 1.0011, "cv_rel_amplitude": 0.0272, "seq_rel_amplitude": 0.290621, "seqslope_rel_amplitude": -0.004138, "mean_power": 267660.6624, "cv_power": 0.0685, "seq_power": 0.717125, "seqslope_power": -6079.238214, "mean_peak_open_vel": 1711.6147, "cv_peak_open_vel": 0.055, "seq_peak_open_vel": 0.479764, "seqslope_peak_open_vel": -16.866071, "mean_peak_close_vel": -2201.4265, "cv_peak_close_vel": 0.0359, "seq_peak_close_vel": 0.253049, "seqslope_peak_close_vel": -21.335714, "mean_mean_open_vel": 982.31, "cv_mean_open_vel": 0.1009, "seq_mean_open_vel": 0.00307, "seqslope_mean_open_vel": -1.90631, "mean_mean_close_vel": -1582.2982, "cv_mean_close_vel": 0.1097, "seq_mean_close_vel": 0.002526, "seqslope_mean_close_vel": 4.722262, "frequency": 2.9087}, {"name": "PD10", "diagnosis": "PD", "event_source": "saved", "has_saved_events": true, "has_complete_events": true, "last_dose_raw": "6h", "time_since_dose_min": 360.0, "levodopa_off": false, "laterality_raw": "L", "laterality_side": "L", "mean_imi": 0.2644, "cv_imi": 0.2255, "seq_imi": 0.112008, "seqslope_imi": -0.0015, "mean_amplitude": 105.4927, "cv_amplitude": 0.2924, "seq_amplitude": 0.662629, "seqslope_amplitude": -2.065069, "mean_rel_amplitude": 1.0268, "cv_rel_amplitude": 0.2702, "seq_rel_amplitude": 0.00318, "seqslope_rel_amplitude": 0.001145, "mean_power": 127465.7493, "cv_power": 0.5183, "seq_power": 0.676313, "seqslope_power": -4517.808824, "mean_peak_open_vel": 1118.2007, "cv_peak_open_vel": 0.3404, "seq_peak_open_vel": 0.601011, "seqslope_peak_open_vel": -24.437601, "mean_peak_close_vel": -1401.4516, "cv_peak_close_vel": 0.3699, "seq_peak_close_vel": 0.663023, "seqslope_peak_close_vel": -34.793908, "mean_mean_open_vel": 833.332, "cv_mean_open_vel": 0.242, "seq_mean_open_vel": 0.195736, "seqslope_mean_open_vel": -7.029924, "mean_mean_close_vel": -1082.2704, "cv_mean_close_vel": 0.2975, "seq_mean_close_vel": 0.345942, "seqslope_mean_close_vel": -15.594256, "frequency": 3.7821}, {"name": "PSP01", "diagnosis": "PSP", "event_source": "saved", "has_saved_events": true, "has_complete_events": true, "last_dose_raw": "-", "time_since_dose_min": null, "levodopa_off": false, "laterality_raw": "L", "laterality_side": "L", "mean_imi": 0.2828, "cv_imi": 0.0819, "seq_imi": 0.167399, "seqslope_imi": -0.000556, "mean_amplitude": 47.0843, "cv_amplitude": 0.2619, "seq_amplitude": 0.492936, "seqslope_amplitude": -0.499903, "mean_rel_amplitude": 0.9926, "cv_rel_amplitude": 0.1735, "seq_rel_amplitude": 0.004297, "seqslope_rel_amplitude": 0.000663, "mean_power": 26168.0742, "cv_power": 0.9017, "seq_power": 0.246575, "seqslope_power": -676.569386, "mean_peak_open_vel": 511.14, "cv_peak_open_vel": 0.3678, "seq_peak_open_vel": 0.348882, "seqslope_peak_open_vel": -6.412315, "mean_peak_close_vel": -581.0925, "cv_peak_close_vel": 0.1968, "seq_peak_close_vel": 0.45652, "seqslope_peak_close_vel": -4.46096, "mean_mean_open_vel": 398.6617, "cv_mean_open_vel": 0.1815, "seq_mean_open_vel": 0.251677, "seqslope_mean_open_vel": -2.096541, "mean_mean_close_vel": -474.4362, "cv_mean_close_vel": 0.2103, "seq_mean_close_vel": 0.261903, "seqslope_mean_close_vel": -2.947981, "frequency": 3.5361}, {"name": "PSP02", "diagnosis": "PSP", "event_source": "saved", "has_saved_events": true, "has_complete_events": true, "last_dose_raw": "? (Appt time 2:30 pm)", "time_since_dose_min": null, "levodopa_off": false, "laterality_raw": "R", "laterality_side": "R", "mean_imi": 2.5625, "cv_imi": 0.3013, "seq_imi": 0.2373, "seqslope_imi": -0.173282, "mean_amplitude": 77.3253, "cv_amplitude": 0.2311, "seq_amplitude": 0.864572, "seqslope_amplitude": -6.35075, "mean_rel_amplitude": 1.0182, "cv_rel_amplitude": 0.2865, "seq_rel_amplitude": 0.208068, "seqslope_rel_amplitude": -0.053419, "mean_power": 15366.9906, "cv_power": 0.4479, "seq_power": 0.374286, "seqslope_power": -957.85473, "mean_peak_open_vel": 200.5031, "cv_peak_open_vel": 0.3675, "seq_peak_open_vel": 0.274463, "seqslope_peak_open_vel": 1.274881, "mean_peak_close_vel": -311.0206, "cv_peak_close_vel": 0.3417, "seq_peak_close_vel": 0.123475, "seqslope_peak_close_vel": 8.564531, "mean_mean_open_vel": 48.1769, "cv_mean_open_vel": 0.3095, "seq_mean_open_vel": 0.133774, "seqslope_mean_open_vel": -0.412548, "mean_mean_close_vel": -260.6765, "cv_mean_close_vel": 2.0737, "seq_mean_close_vel": 0.185172, "seqslope_mean_close_vel": 4.651406, "frequency": 0.3902}], "groups": ["Control", "MSA", "PD", "PSP"]}